[
  {
    "id": "1",
    "name": "Flip4Flap"
  },
  {
    "id": "2",
    "name": "Demivar"
  },
  {
    "id": "3",
    "name": "Nasa"
  },
  {
    "id": "5",
    "name": "Marez12"
  },
  {
    "id": "6",
    "name": "Mrwhite350"
  },
  {
    "id": "7",
    "name": "[OFCRA] DIEU INDO"
  },
  {
    "id": "9",
    "name": "Manchot"
  },
  {
    "id": "10",
    "name": "[OTEA] Rick_Hunter2"
  },
  {
    "id": "11",
    "name": "beTeka"
  },
  {
    "id": "12",
    "name": "Scott"
  },
  {
    "id": "13",
    "name": "Leboucher"
  },
  {
    "id": "15",
    "name": "2RGT Il Griso"
  },
  {
    "id": "16",
    "name": "2RGT Sirius"
  },
  {
    "id": "19",
    "name": "2RGT ignazio"
  },
  {
    "id": "20",
    "name": "2RGT Pleace"
  },
  {
    "id": "21",
    "name": "2RGT Leeroy Jenkins"
  },
  {
    "id": "22",
    "name": "Reinhardt"
  },
  {
    "id": "23",
    "name": "Radio-Operator Øystein"
  },
  {
    "id": "24",
    "name": "2RGT Tapparella"
  },
  {
    "id": "25",
    "name": "2RGT The sniper"
  },
  {
    "id": "26",
    "name": "2RGT Damned"
  },
  {
    "id": "28",
    "name": "2RGTr Faligator"
  },
  {
    "id": "29",
    "name": "2RGT EagleOne"
  },
  {
    "id": "30",
    "name": "2RGT Spaghetti"
  },
  {
    "id": "31",
    "name": "2RGTr MANDI"
  },
  {
    "id": "33",
    "name": "[GHOST]Kubajs"
  },
  {
    "id": "34",
    "name": "[MOR] Genesis"
  },
  {
    "id": "35",
    "name": "5thPK_GonzoPunkass"
  },
  {
    "id": "36",
    "name": "[MOR] Stealth"
  },
  {
    "id": "37",
    "name": "5thPK_ToxaSM"
  },
  {
    "id": "38",
    "name": "5thPK_KarKarich"
  },
  {
    "id": "39",
    "name": "[MOR] Aja"
  },
  {
    "id": "41",
    "name": "Mr.cool"
  },
  {
    "id": "42",
    "name": "[19th]SomeGuy"
  },
  {
    "id": "43",
    "name": "Jeremy Hotham"
  },
  {
    "id": "44",
    "name": "Max Berry"
  },
  {
    "id": "45",
    "name": "assau"
  },
  {
    "id": "46",
    "name": "Kieran"
  },
  {
    "id": "47",
    "name": "The Mr Dave"
  },
  {
    "id": "49",
    "name": "SzalKrist"
  },
  {
    "id": "50",
    "name": "Michael"
  },
  {
    "id": "51",
    "name": "Ati"
  },
  {
    "id": "52",
    "name": "Doritos"
  },
  {
    "id": "53",
    "name": "N3MO"
  },
  {
    "id": "55",
    "name": "Alfred"
  },
  {
    "id": "56",
    "name": "RuskoFF"
  },
  {
    "id": "57",
    "name": "Risbo"
  },
  {
    "id": "58",
    "name": "menfin"
  },
  {
    "id": "59",
    "name": "N8"
  },
  {
    "id": "60",
    "name": "NINJA MC"
  },
  {
    "id": "62",
    "name": "PvtElder"
  },
  {
    "id": "63",
    "name": "ArracK"
  },
  {
    "id": "64",
    "name": "kutulu"
  },
  {
    "id": "65",
    "name": "Valou"
  },
  {
    "id": "66",
    "name": ".:Sguiz:. [BG21]"
  },
  {
    "id": "67",
    "name": "Zixme"
  },
  {
    "id": "69",
    "name": "{S.A.M} Sixel"
  },
  {
    "id": "70",
    "name": "{S.A.M} Préda"
  },
  {
    "id": "71",
    "name": "{S.A.M} robino"
  },
  {
    "id": "72",
    "name": "{S.A.M} Zaidah"
  },
  {
    "id": "73",
    "name": "Valkyrie"
  },
  {
    "id": "74",
    "name": "{S.A.M} Alex-12"
  },
  {
    "id": "75",
    "name": "{S.A.M} Sauronox"
  },
  {
    "id": "76",
    "name": "{S.A.M} Benoit Jouanno"
  },
  {
    "id": "77",
    "name": "{S.A.M} Startek17"
  },
  {
    "id": "79",
    "name": "vincent"
  },
  {
    "id": "80",
    "name": "latrufe[OFCRA]"
  },
  {
    "id": "81",
    "name": "{S.A.M} Reznor"
  },
  {
    "id": "82",
    "name": "{S.A.M} Sons83"
  },
  {
    "id": "83",
    "name": "{S.A.M} Anthony Stark"
  },
  {
    "id": "84",
    "name": "2RGT Haldir"
  },
  {
    "id": "85",
    "name": "2RGT Zerogravity"
  },
  {
    "id": "86",
    "name": "2RGTr Gippa"
  },
  {
    "id": "87",
    "name": "2RGT Rikysav"
  },
  {
    "id": "88",
    "name": "2RGT Beckerman"
  },
  {
    "id": "91",
    "name": "Fleche"
  },
  {
    "id": "92",
    "name": "Arthyc"
  },
  {
    "id": "93",
    "name": "2RGT OBERST"
  },
  {
    "id": "94",
    "name": "2RGT Smilzo"
  },
  {
    "id": "95",
    "name": "2RGT Cobra"
  },
  {
    "id": "96",
    "name": "2RGT Faligator"
  },
  {
    "id": "97",
    "name": "2RGT FURIOS"
  },
  {
    "id": "98",
    "name": "2RGTr Anam"
  },
  {
    "id": "99",
    "name": "Salsa"
  },
  {
    "id": "102",
    "name": "majax"
  },
  {
    "id": "103",
    "name": "Jo Le Trembleur"
  },
  {
    "id": "104",
    "name": "Gimlur"
  },
  {
    "id": "105",
    "name": "{S.A.M} orglobe"
  },
  {
    "id": "107",
    "name": "pifmage"
  },
  {
    "id": "108",
    "name": "flo"
  },
  {
    "id": "109",
    "name": "Parthius"
  },
  {
    "id": "110",
    "name": "Drangon Lee"
  },
  {
    "id": "111",
    "name": "Le Brun"
  },
  {
    "id": "112",
    "name": "Nade"
  },
  {
    "id": "113",
    "name": "Karadoc"
  },
  {
    "id": "114",
    "name": "#NOM ?"
  },
  {
    "id": "115",
    "name": "[OTEA] Clem"
  },
  {
    "id": "116",
    "name": "[SGT]Jentlemen"
  },
  {
    "id": "117",
    "name": "Guttormsen"
  },
  {
    "id": "118",
    "name": "Barden"
  },
  {
    "id": "119",
    "name": "TeTeT"
  },
  {
    "id": "120",
    "name": "cptwalker"
  },
  {
    "id": "121",
    "name": "Lakarak"
  },
  {
    "id": "122",
    "name": "PFC D. Thompson"
  },
  {
    "id": "123",
    "name": "Leboucher60"
  },
  {
    "id": "124",
    "name": "[Cpl] Darkling"
  },
  {
    "id": "125",
    "name": "PTE_EnigmaUK"
  },
  {
    "id": "126",
    "name": "DoC_WeeDoW"
  },
  {
    "id": "127",
    "name": "Haytham"
  },
  {
    "id": "128",
    "name": "Maxsimilian Moloko"
  },
  {
    "id": "130",
    "name": "Eralorn"
  },
  {
    "id": "131",
    "name": "BlackHart"
  },
  {
    "id": "132",
    "name": "Kyuss"
  },
  {
    "id": "133",
    "name": "Baal-Hadad"
  },
  {
    "id": "134",
    "name": "Steel"
  },
  {
    "id": "135",
    "name": "Thomas"
  },
  {
    "id": "137",
    "name": "jossomjod"
  },
  {
    "id": "138",
    "name": "Freedman"
  },
  {
    "id": "139",
    "name": "UberPP"
  },
  {
    "id": "140",
    "name": "Bear"
  },
  {
    "id": "141",
    "name": "Phil"
  },
  {
    "id": "142",
    "name": "1SG LeClair [75th RRC]"
  },
  {
    "id": "143",
    "name": "SFC Langowski [75th RRC]"
  },
  {
    "id": "144",
    "name": "SSG. Silver"
  },
  {
    "id": "145",
    "name": "Capt B. Wagner"
  },
  {
    "id": "146",
    "name": "Lt M. Haris"
  },
  {
    "id": "147",
    "name": "B. Beaumont"
  },
  {
    "id": "148",
    "name": "Boutin"
  },
  {
    "id": "149",
    "name": "caleb"
  },
  {
    "id": "150",
    "name": "SFC Hildreth [75th RRC]"
  },
  {
    "id": "151",
    "name": "J. Beach"
  },
  {
    "id": "152",
    "name": "Pnutz"
  },
  {
    "id": "153",
    "name": "SSgt Fish"
  },
  {
    "id": "154",
    "name": "zuluNiner"
  },
  {
    "id": "155",
    "name": "2RGT Cesare"
  },
  {
    "id": "156",
    "name": "2RGTr NoxMight"
  },
  {
    "id": "158",
    "name": "2RGT Lupo"
  },
  {
    "id": "159",
    "name": "2RGT HOLLYwood"
  },
  {
    "id": "160",
    "name": "MadWolf"
  },
  {
    "id": "161",
    "name": "pj83"
  },
  {
    "id": "162",
    "name": "Spads"
  },
  {
    "id": "163",
    "name": "[OFCRA]Harine"
  },
  {
    "id": "164",
    "name": "Belmont"
  },
  {
    "id": "165",
    "name": "{S.A.M.} Valkyrie"
  },
  {
    "id": "166",
    "name": "InsideReality"
  },
  {
    "id": "167",
    "name": "{S.A.M} Savoiecraft74"
  },
  {
    "id": "168",
    "name": "Wigster600"
  },
  {
    "id": "169",
    "name": "Marko"
  },
  {
    "id": "170",
    "name": "Jeb Bush"
  },
  {
    "id": "172",
    "name": "Mtb.Lemoigne-1Sap"
  },
  {
    "id": "173",
    "name": "Qm2.Neven-8Vol"
  },
  {
    "id": "174",
    "name": "Qm2.Croizer-1Tp"
  },
  {
    "id": "176",
    "name": "Qm2.Hattu-1Vol"
  },
  {
    "id": "177",
    "name": "Qm1.Guillou-8-Fsl"
  },
  {
    "id": "178",
    "name": "Mtb.Salaün-QGPil"
  },
  {
    "id": "179",
    "name": "Mtl.Dechamboux - KGFsl"
  },
  {
    "id": "181",
    "name": "Shweik"
  },
  {
    "id": "183",
    "name": "Rasty69svk"
  },
  {
    "id": "184",
    "name": "Sebastiaan"
  },
  {
    "id": "185",
    "name": "BBOYSNAKEDOGG"
  },
  {
    "id": "186",
    "name": "2RGTr Tremor199"
  },
  {
    "id": "187",
    "name": "Bluck"
  },
  {
    "id": "188",
    "name": "Steffan"
  },
  {
    "id": "189",
    "name": "{S.A.M} Durbo"
  },
  {
    "id": "190",
    "name": "Alexander6377"
  },
  {
    "id": "191",
    "name": "BNS BBOYSNAKEDOGG"
  },
  {
    "id": "192",
    "name": "BNS Marko"
  },
  {
    "id": "193",
    "name": "BNS ShadowDK"
  },
  {
    "id": "194",
    "name": "BNS Kinghaas"
  },
  {
    "id": "195",
    "name": "Speedy"
  },
  {
    "id": "197",
    "name": "N8RAH"
  },
  {
    "id": "198",
    "name": "jance"
  },
  {
    "id": "200",
    "name": "Koresten"
  },
  {
    "id": "202",
    "name": "[=BTK=] Krysak"
  },
  {
    "id": "203",
    "name": "2RGT Rei"
  },
  {
    "id": "204",
    "name": "Proipod"
  },
  {
    "id": "205",
    "name": "Qm2.Salaün-1Ast"
  },
  {
    "id": "207",
    "name": "Qm2.De Naurois-1Lav"
  },
  {
    "id": "208",
    "name": "Mtl.Ravel-1Tp"
  },
  {
    "id": "209",
    "name": "M.Labas-KGCmd"
  },
  {
    "id": "210",
    "name": "Sm2.Guillou-8-Cmd"
  },
  {
    "id": "211",
    "name": "Mtl.Cartier-QGFsl"
  },
  {
    "id": "213",
    "name": "[CTU] LEYDEN"
  },
  {
    "id": "214",
    "name": "Blackout"
  },
  {
    "id": "216",
    "name": "Fenrir"
  },
  {
    "id": "217",
    "name": "Norah"
  },
  {
    "id": "218",
    "name": "2RGT Gekroon"
  },
  {
    "id": "219",
    "name": "Minutemen Parthius"
  },
  {
    "id": "221",
    "name": "Harine"
  },
  {
    "id": "223",
    "name": "PrOiP"
  },
  {
    "id": "224",
    "name": "Sachy"
  },
  {
    "id": "225",
    "name": "osmen"
  },
  {
    "id": "226",
    "name": "[C.S.E.C] Kadlik"
  },
  {
    "id": "227",
    "name": "[MOR] Spreekill"
  },
  {
    "id": "228",
    "name": "Xaverius"
  },
  {
    "id": "229",
    "name": "Islambek"
  },
  {
    "id": "230",
    "name": "Sea Otter"
  },
  {
    "id": "231",
    "name": "[C.S.E.C] Daark"
  },
  {
    "id": "233",
    "name": "|ToK|OttO-Tr"
  },
  {
    "id": "234",
    "name": "[ToK] Jensarray"
  },
  {
    "id": "235",
    "name": "|ToK|Karo"
  },
  {
    "id": "236",
    "name": "[ToK]Alcolique"
  },
  {
    "id": "237",
    "name": "|ToK|Karahilal"
  },
  {
    "id": "238",
    "name": "|ToK|Panzer"
  },
  {
    "id": "239",
    "name": "Skuul"
  },
  {
    "id": "240",
    "name": "Razmo"
  },
  {
    "id": "241",
    "name": "[C.S.E.C]Jfafek"
  },
  {
    "id": "242",
    "name": "[C.S.E.C] Tankac"
  },
  {
    "id": "243",
    "name": "SiyahSancak"
  },
  {
    "id": "244",
    "name": "|ToK|Broklins"
  },
  {
    "id": "245",
    "name": "Le-Sarde-Fr"
  },
  {
    "id": "246",
    "name": "vince-one"
  },
  {
    "id": "247",
    "name": "Franco"
  },
  {
    "id": "248",
    "name": "Prax"
  },
  {
    "id": "249",
    "name": "Pascal"
  },
  {
    "id": "250",
    "name": "2RGT Anam"
  },
  {
    "id": "251",
    "name": "2RGTr Francesco"
  },
  {
    "id": "252",
    "name": "Kali S"
  },
  {
    "id": "253",
    "name": "Kaubanga"
  },
  {
    "id": "254",
    "name": "[FJB49]Roland"
  },
  {
    "id": "255",
    "name": "Marf"
  },
  {
    "id": "256",
    "name": "Bexi"
  },
  {
    "id": "257",
    "name": "FoxHound"
  },
  {
    "id": "258",
    "name": "Thomas M."
  },
  {
    "id": "259",
    "name": "Cadet.Lofi-1Fsl"
  },
  {
    "id": "260",
    "name": "Sm1.Guillou-8-Cmd"
  },
  {
    "id": "261",
    "name": "Sm2.Gauthier-QGCmd"
  },
  {
    "id": "263",
    "name": "Mtl.Meudal-8Sap [CK]"
  },
  {
    "id": "264",
    "name": "Qm2.Dechamboux-KGVol"
  },
  {
    "id": "265",
    "name": "Mtl.Guy-1Inf"
  },
  {
    "id": "266",
    "name": "Pogo_"
  },
  {
    "id": "269",
    "name": "19th Doritos"
  },
  {
    "id": "270",
    "name": "19th Rico"
  },
  {
    "id": "271",
    "name": "J. Doberman"
  },
  {
    "id": "272",
    "name": "Timms"
  },
  {
    "id": "273",
    "name": "finch"
  },
  {
    "id": "274",
    "name": "senis"
  },
  {
    "id": "275",
    "name": "strele"
  },
  {
    "id": "276",
    "name": "Beneris"
  },
  {
    "id": "277",
    "name": "Jura"
  },
  {
    "id": "278",
    "name": "Stormed"
  },
  {
    "id": "279",
    "name": "Alan"
  },
  {
    "id": "280",
    "name": "Arrow1988"
  },
  {
    "id": "281",
    "name": "Jager"
  },
  {
    "id": "282",
    "name": "Layra"
  },
  {
    "id": "283",
    "name": "Helmut"
  },
  {
    "id": "284",
    "name": "[OF] TPEMOP"
  },
  {
    "id": "285",
    "name": "Romualdas"
  },
  {
    "id": "286",
    "name": "Red"
  },
  {
    "id": "287",
    "name": "IMI_CZ"
  },
  {
    "id": "288",
    "name": "Resurge"
  },
  {
    "id": "290",
    "name": "Panzer"
  },
  {
    "id": "291",
    "name": "|ToK|sOfOo15"
  },
  {
    "id": "292",
    "name": "ENES"
  },
  {
    "id": "294",
    "name": "StobZ"
  },
  {
    "id": "295",
    "name": "Mr Propre"
  },
  {
    "id": "296",
    "name": "CSF_Gladio"
  },
  {
    "id": "297",
    "name": "CSF_Zajcev"
  },
  {
    "id": "298",
    "name": "CSF_Tommy"
  },
  {
    "id": "299",
    "name": "CSF_Putin"
  },
  {
    "id": "300",
    "name": "CSF_Fiach"
  },
  {
    "id": "301",
    "name": "CSF_Sousuke"
  },
  {
    "id": "302",
    "name": "Qm1.Dechamboux-KGVol"
  },
  {
    "id": "303",
    "name": "Lv.Fourer-QGCmd"
  },
  {
    "id": "305",
    "name": "Mtb.Hubert-KGStn"
  },
  {
    "id": "306",
    "name": "Qm2.Le Goff-8Vol"
  },
  {
    "id": "309",
    "name": "Mtl.Cartier-1Fsl"
  },
  {
    "id": "310",
    "name": "Qm2.De Naurois-1Fsl"
  },
  {
    "id": "311",
    "name": "CSF_Fox"
  },
  {
    "id": "312",
    "name": "CSF_Zeda"
  },
  {
    "id": "313",
    "name": "rek. OndrejLalo"
  },
  {
    "id": "314",
    "name": "Kryss"
  },
  {
    "id": "315",
    "name": "Palladium"
  },
  {
    "id": "316",
    "name": "Sons83"
  },
  {
    "id": "319",
    "name": "Paul Smith [OFCRA]"
  },
  {
    "id": "320",
    "name": "Mtl.Bougrain-8Fsl"
  },
  {
    "id": "321",
    "name": "Mtl.Maler-QGPlt"
  },
  {
    "id": "322",
    "name": "Mtl.Roelandt-8Fsl"
  },
  {
    "id": "323",
    "name": "Qm2.Salaün-1Vol"
  },
  {
    "id": "324",
    "name": "Qm1.Neven-8Stn"
  },
  {
    "id": "325",
    "name": "Mtb.Meudal-8Sap"
  },
  {
    "id": "326",
    "name": "|ToK|santona"
  },
  {
    "id": "327",
    "name": "|ToK|Kaan"
  },
  {
    "id": "328",
    "name": "|ToK|UnsaL"
  },
  {
    "id": "329",
    "name": "[ToK]Tyger"
  },
  {
    "id": "334",
    "name": "5thPK_37mm"
  },
  {
    "id": "335",
    "name": "Spiter"
  },
  {
    "id": "336",
    "name": "[CTU] Miguel"
  },
  {
    "id": "337",
    "name": "|CTU| Braian"
  },
  {
    "id": "338",
    "name": "[MOR] Panther"
  },
  {
    "id": "339",
    "name": "[C.S.E.C] Seal Willm"
  },
  {
    "id": "340",
    "name": "Hall"
  },
  {
    "id": "341",
    "name": "Brewer"
  },
  {
    "id": "342",
    "name": "COINcidence"
  },
  {
    "id": "343",
    "name": "FALKLANDSISOURS"
  },
  {
    "id": "344",
    "name": "Garrett Hawke"
  },
  {
    "id": "347",
    "name": "Hippie"
  },
  {
    "id": "348",
    "name": "USER"
  },
  {
    "id": "350",
    "name": "Jacob Rees-Mogg"
  },
  {
    "id": "351",
    "name": "Alton Alfalan"
  },
  {
    "id": "352",
    "name": "Phk4900"
  },
  {
    "id": "356",
    "name": "mrdland"
  },
  {
    "id": "359",
    "name": "Qm1.Dechamboux - KgFsl"
  },
  {
    "id": "361",
    "name": "Mtb.Letang-KGLav"
  },
  {
    "id": "362",
    "name": "Mtl.Roelandt-8Inf"
  },
  {
    "id": "363",
    "name": "Mtb.De Naurois-1Lav"
  },
  {
    "id": "364",
    "name": "Mtl.Horny-KGVol"
  },
  {
    "id": "365",
    "name": "Mtl.Laventure KGFSap"
  },
  {
    "id": "366",
    "name": "Qm2.Meudal-8Sap"
  },
  {
    "id": "367",
    "name": "Hunter95"
  },
  {
    "id": "368",
    "name": "Troy"
  },
  {
    "id": "369",
    "name": "Foxy"
  },
  {
    "id": "370",
    "name": "[19th]FrenchFlipoFlapo"
  },
  {
    "id": "371",
    "name": "|ToK|SkyWolf"
  },
  {
    "id": "372",
    "name": "Mtb.Roelandt-8Inf"
  },
  {
    "id": "373",
    "name": "Cadet.Fougère-8Fsl"
  },
  {
    "id": "374",
    "name": "Mogwaii"
  },
  {
    "id": "375",
    "name": "[1er R.C.C] mrdland"
  },
  {
    "id": "376",
    "name": "STARGHOST"
  },
  {
    "id": "377",
    "name": "Plague Doctor"
  },
  {
    "id": "378",
    "name": "Tequiller"
  },
  {
    "id": "379",
    "name": "Haralt Sokolov"
  },
  {
    "id": "380",
    "name": "2RGTr VeRGiL"
  },
  {
    "id": "381",
    "name": "Nicola"
  },
  {
    "id": "382",
    "name": "GySgt. Pipin"
  },
  {
    "id": "383",
    "name": "Cheez"
  },
  {
    "id": "384",
    "name": "Holo"
  },
  {
    "id": "385",
    "name": "AndrewCZE"
  },
  {
    "id": "386",
    "name": "Oragann"
  },
  {
    "id": "387",
    "name": "Serza"
  },
  {
    "id": "388",
    "name": "[BTK] Rasty69"
  },
  {
    "id": "389",
    "name": "[MOR] Beast"
  },
  {
    "id": "390",
    "name": "Hawt_Sauce"
  },
  {
    "id": "391",
    "name": "beregbalu"
  },
  {
    "id": "394",
    "name": "MD"
  },
  {
    "id": "395",
    "name": "Khabib"
  },
  {
    "id": "396",
    "name": "Cpt.C.Bollore-QGCmd"
  },
  {
    "id": "397",
    "name": "Mtb.Roelandt-8Tp"
  },
  {
    "id": "398",
    "name": "Qm2.Hubert-KGStn"
  },
  {
    "id": "399",
    "name": "Mtb.Horny-KGVol"
  },
  {
    "id": "400",
    "name": "Lucterro"
  },
  {
    "id": "401",
    "name": "DarkNeo"
  },
  {
    "id": "402",
    "name": "Pipin"
  },
  {
    "id": "403",
    "name": "houzdaa"
  },
  {
    "id": "404",
    "name": "KRMI"
  },
  {
    "id": "406",
    "name": "M.Guillou-8Cmd"
  },
  {
    "id": "407",
    "name": "Marechaldu80"
  },
  {
    "id": "408",
    "name": "Pfc.Salaün"
  },
  {
    "id": "409",
    "name": "DjMtv"
  },
  {
    "id": "412",
    "name": "Jordan"
  },
  {
    "id": "413",
    "name": "Bang Ding Ow"
  },
  {
    "id": "414",
    "name": "Guang Fei"
  },
  {
    "id": "416",
    "name": "Zhuge Liang"
  },
  {
    "id": "417",
    "name": "Chairman Mao"
  },
  {
    "id": "418",
    "name": "Ho Lee Fuk"
  },
  {
    "id": "421",
    "name": "Mtb.Scherer-KGFsl"
  },
  {
    "id": "422",
    "name": "Nanking"
  },
  {
    "id": "423",
    "name": "xaver"
  },
  {
    "id": "424",
    "name": "GoatLand"
  },
  {
    "id": "426",
    "name": "[FOX]Visu"
  },
  {
    "id": "427",
    "name": "[MOR] Jerenor"
  },
  {
    "id": "428",
    "name": "5thPK_Octopus"
  },
  {
    "id": "430",
    "name": "[C.S.E.C] BannanaMan"
  },
  {
    "id": "431",
    "name": "[BTK] Hall"
  },
  {
    "id": "432",
    "name": "[C.S.E.C] TheVeverka"
  },
  {
    "id": "433",
    "name": "lokootoc"
  },
  {
    "id": "434",
    "name": "Egnaterus"
  },
  {
    "id": "435",
    "name": "Karhal"
  },
  {
    "id": "436",
    "name": "TheGatz"
  },
  {
    "id": "437",
    "name": "MANY"
  },
  {
    "id": "438",
    "name": "Sirup"
  },
  {
    "id": "439",
    "name": "Jfafek"
  },
  {
    "id": "440",
    "name": "Warran"
  },
  {
    "id": "441",
    "name": "Tortas"
  },
  {
    "id": "442",
    "name": "Noobas13"
  },
  {
    "id": "445",
    "name": "[19th] Rico"
  },
  {
    "id": "446",
    "name": "2RGTr Magnvus"
  },
  {
    "id": "447",
    "name": "Olaf Forge Lune"
  },
  {
    "id": "448",
    "name": "Unicorne"
  },
  {
    "id": "449",
    "name": "Bex"
  },
  {
    "id": "450",
    "name": "LONS"
  },
  {
    "id": "451",
    "name": "[S.F.C.]Jfafek"
  },
  {
    "id": "452",
    "name": "[LcG] DeLaCour"
  },
  {
    "id": "453",
    "name": "[TON] Sauronpmc"
  },
  {
    "id": "454",
    "name": "Skyline"
  },
  {
    "id": "455",
    "name": "Katyusha"
  },
  {
    "id": "456",
    "name": "Vic33740"
  },
  {
    "id": "457",
    "name": "Mp.Labas"
  },
  {
    "id": "458",
    "name": "Mtb.De Naurois 1lav"
  },
  {
    "id": "459",
    "name": "[BTK]Koresten"
  },
  {
    "id": "460",
    "name": "espartakus94"
  },
  {
    "id": "461",
    "name": "SgtM Mercenario"
  },
  {
    "id": "462",
    "name": "Cbo Magnetar"
  },
  {
    "id": "463",
    "name": "Sdo Astur"
  },
  {
    "id": "464",
    "name": "Sdo1 Juanma"
  },
  {
    "id": "465",
    "name": "Sdo Rambo"
  },
  {
    "id": "466",
    "name": "Cbo Fort"
  },
  {
    "id": "467",
    "name": "Sdo TrosKa"
  },
  {
    "id": "468",
    "name": "Tte RanTa"
  },
  {
    "id": "469",
    "name": "Atli Mortensen"
  },
  {
    "id": "470",
    "name": "2RGTr Fred"
  },
  {
    "id": "471",
    "name": "2RGTr Zeus751"
  },
  {
    "id": "472",
    "name": "2RGTr Vittorio"
  },
  {
    "id": "473",
    "name": "Greg"
  },
  {
    "id": "474",
    "name": "Miguel Riviera"
  },
  {
    "id": "475",
    "name": "Cadet.Monceau-1Fsl"
  },
  {
    "id": "476",
    "name": "Mtb.Richen-1Sap"
  },
  {
    "id": "477",
    "name": "2RGT VeRGiL"
  },
  {
    "id": "478",
    "name": "Yalamano Plüsch"
  },
  {
    "id": "479",
    "name": "CSF_Dog"
  },
  {
    "id": "480",
    "name": "CSF_Lollo"
  },
  {
    "id": "481",
    "name": "Mp.Labas-KGCmd"
  },
  {
    "id": "482",
    "name": "Mtb.Vinat-QG.Med"
  },
  {
    "id": "483",
    "name": "Anox."
  },
  {
    "id": "484",
    "name": "[1er R.C.C] TheKillian"
  },
  {
    "id": "485",
    "name": "[1er R.C.C] O.Forge Lune"
  },
  {
    "id": "486",
    "name": "[1er R.C.C] Tequiller"
  },
  {
    "id": "487",
    "name": "[1er R.C.C] Purem"
  },
  {
    "id": "488",
    "name": "[1er R.C.C] Cardifure"
  },
  {
    "id": "489",
    "name": "Mtl.Priez-KGFsl"
  },
  {
    "id": "490",
    "name": "Qm2.Horny-KGVol"
  },
  {
    "id": "491",
    "name": "Mtl.Monceau-1Inf"
  },
  {
    "id": "492",
    "name": "CSF_Snail"
  },
  {
    "id": "493",
    "name": "Zalox"
  },
  {
    "id": "495",
    "name": "=S.O.F=Niklas Ky"
  },
  {
    "id": "496",
    "name": "[1er R.C.C] Egregoros"
  },
  {
    "id": "497",
    "name": "Qm2.Roelandt-8Tp"
  },
  {
    "id": "498",
    "name": "Cadet.Fougere-1Fsl"
  },
  {
    "id": "499",
    "name": "Cadet.Wallen-1Fsl"
  },
  {
    "id": "500",
    "name": "Elberg"
  },
  {
    "id": "502",
    "name": "Benoit"
  },
  {
    "id": "503",
    "name": "2RGT Fred"
  },
  {
    "id": "504",
    "name": "SomeGuy"
  },
  {
    "id": "505",
    "name": "Jay Baited"
  },
  {
    "id": "506",
    "name": "FJB49 | Bex"
  },
  {
    "id": "507",
    "name": "2RGT Magnvus"
  },
  {
    "id": "508",
    "name": "[1er R.C.C] Miguel"
  },
  {
    "id": "509",
    "name": "[OFCRA] Anox."
  },
  {
    "id": "511",
    "name": "[1er R.C.C] Starghost"
  },
  {
    "id": "512",
    "name": "[SOB] Dead"
  },
  {
    "id": "513",
    "name": "[SOB] bux"
  },
  {
    "id": "514",
    "name": "[SOB] Feldi1993"
  },
  {
    "id": "515",
    "name": "[SOB] Sulli"
  },
  {
    "id": "516",
    "name": "[SOB] Dennis"
  },
  {
    "id": "517",
    "name": "Tobias"
  },
  {
    "id": "519",
    "name": "Cbo Gisby"
  },
  {
    "id": "520",
    "name": "Sdo Chacal"
  },
  {
    "id": "521",
    "name": "Sdo Fonfo"
  },
  {
    "id": "522",
    "name": "Sdo Incongo"
  },
  {
    "id": "523",
    "name": "Sdo espartakus94"
  },
  {
    "id": "524",
    "name": "Sdo Murdock"
  },
  {
    "id": "525",
    "name": "Redleouf"
  },
  {
    "id": "526",
    "name": "Destiny [19th]"
  },
  {
    "id": "527",
    "name": "Bexx"
  },
  {
    "id": "528",
    "name": "[MOR] Masaker"
  },
  {
    "id": "529",
    "name": "Antispote"
  },
  {
    "id": "530",
    "name": "Fact of house Logic"
  },
  {
    "id": "531",
    "name": "MOoriiii"
  },
  {
    "id": "532",
    "name": "Hyver"
  },
  {
    "id": "533",
    "name": "CSF_Hydro"
  },
  {
    "id": "534",
    "name": "CSF_Flanker"
  },
  {
    "id": "535",
    "name": "Aaron"
  },
  {
    "id": "536",
    "name": "[1er R.C.C]Plague Doctor"
  },
  {
    "id": "537",
    "name": "Qm2.Salaün-1Stn"
  },
  {
    "id": "538",
    "name": "Le_Fossoyeur"
  },
  {
    "id": "539",
    "name": "Panther"
  },
  {
    "id": "540",
    "name": "#NOM?"
  },
  {
    "id": "541",
    "name": "Appe"
  },
  {
    "id": "542",
    "name": "Vergil"
  },
  {
    "id": "543",
    "name": "Sdo Marian"
  },
  {
    "id": "544",
    "name": "Brig GoStRoM"
  },
  {
    "id": "545",
    "name": "Wiljos"
  },
  {
    "id": "546",
    "name": "Cbo Awizor"
  },
  {
    "id": "547",
    "name": "Mtl.Fougere-1Fsl"
  },
  {
    "id": "548",
    "name": "Mtb.Faure-8Inf"
  },
  {
    "id": "549",
    "name": "Mtl.Wallen-1Ast"
  },
  {
    "id": "550",
    "name": "[1er R.C.C] Shades"
  },
  {
    "id": "551",
    "name": "Rek"
  },
  {
    "id": "552",
    "name": "[1er R.C.C] Motman"
  },
  {
    "id": "553",
    "name": "aaron"
  },
  {
    "id": "554",
    "name": "[FJB49] Ezio"
  },
  {
    "id": "555",
    "name": "[1er R.C.C] Rek"
  },
  {
    "id": "556",
    "name": "Mtb.Barbe-8Ast"
  },
  {
    "id": "557",
    "name": "CSF_Tiger"
  },
  {
    "id": "558",
    "name": "[C.S.E.C] Ziki_CZ"
  },
  {
    "id": "559",
    "name": "=S.O.F=Aaron"
  },
  {
    "id": "562",
    "name": "Qm1.Roelandt-8Tp"
  },
  {
    "id": "563",
    "name": "Qm1.Scherer-KGTp"
  },
  {
    "id": "564",
    "name": "Mtb.Pinelli-KGInf"
  },
  {
    "id": "565",
    "name": "Qm2.Faure-8Inf"
  },
  {
    "id": "566",
    "name": "[1er R.C.C] Manéalys"
  },
  {
    "id": "569",
    "name": "2RGTr Medellin"
  },
  {
    "id": "571",
    "name": "Jaxhunt3r"
  },
  {
    "id": "572",
    "name": "Owen"
  },
  {
    "id": "573",
    "name": "Qm2.Letang-KGLav"
  },
  {
    "id": "575",
    "name": "Qm2.Senée-1Ast"
  },
  {
    "id": "576",
    "name": "Serguei"
  },
  {
    "id": "578",
    "name": "Gerinomius"
  },
  {
    "id": "579",
    "name": "Lt. Morel (djazore"
  },
  {
    "id": "580",
    "name": "Sch. F. Pichon (Shiffty"
  },
  {
    "id": "581",
    "name": "Cpl. Poleski (SmK [TON]"
  },
  {
    "id": "582",
    "name": "Narko [ Rossi ]"
  },
  {
    "id": "583",
    "name": "Cpt.Carter (logO"
  },
  {
    "id": "584",
    "name": "Etoile du Matin"
  },
  {
    "id": "585",
    "name": "Malte"
  },
  {
    "id": "586",
    "name": "Sdo Mik"
  },
  {
    "id": "587",
    "name": "Sdo1 Fort"
  },
  {
    "id": "588",
    "name": "[OFCRA]Daedalus"
  },
  {
    "id": "589",
    "name": "Sgt.S.Vauban (Aigle2"
  },
  {
    "id": "590",
    "name": "tch3tchN"
  },
  {
    "id": "591",
    "name": "Mtl.Fougere-1Stn"
  },
  {
    "id": "592",
    "name": "Mtl.Rousseau-1Fsl [CK]"
  },
  {
    "id": "593",
    "name": "Qm1.Roelandt-8Fsl"
  },
  {
    "id": "594",
    "name": "YeanLucReupTon"
  },
  {
    "id": "595",
    "name": "Dylan"
  },
  {
    "id": "596",
    "name": "LittleCapt"
  },
  {
    "id": "597",
    "name": "ZartaK32"
  },
  {
    "id": "598",
    "name": "sybren"
  },
  {
    "id": "599",
    "name": "Qatanov"
  },
  {
    "id": "600",
    "name": "Fuchs"
  },
  {
    "id": "601",
    "name": "[BTK] Red"
  },
  {
    "id": "602",
    "name": "[BTK] Shweik"
  },
  {
    "id": "603",
    "name": "Diavel"
  },
  {
    "id": "604",
    "name": "haxey"
  },
  {
    "id": "605",
    "name": "Moloko"
  },
  {
    "id": "606",
    "name": "Qm1.Richemont-1Fsl"
  },
  {
    "id": "607",
    "name": "Mtb.Neven-8Inf"
  },
  {
    "id": "608",
    "name": "Cadet.Ravel-8Fsl"
  },
  {
    "id": "609",
    "name": "2RGTr Pinza67"
  },
  {
    "id": "610",
    "name": "2RGTr Sipo"
  },
  {
    "id": "611",
    "name": "Maxo Dutch"
  },
  {
    "id": "612",
    "name": "Le Chacal"
  },
  {
    "id": "613",
    "name": "hugob"
  },
  {
    "id": "614",
    "name": "Weber"
  },
  {
    "id": "615",
    "name": "Rycka [LITCON]"
  },
  {
    "id": "616",
    "name": "LIUC"
  },
  {
    "id": "617",
    "name": "karke"
  },
  {
    "id": "618",
    "name": "bogis"
  },
  {
    "id": "619",
    "name": "Mtb.Fougere-1Stn"
  },
  {
    "id": "620",
    "name": "Mtl.Maler-8Vol"
  },
  {
    "id": "621",
    "name": "Tobias Lindner"
  },
  {
    "id": "622",
    "name": "Philitti"
  },
  {
    "id": "623",
    "name": "Cadet.Ropert-1Fsl[CK]"
  },
  {
    "id": "624",
    "name": "Fondas"
  },
  {
    "id": "625",
    "name": "2RGT Saverass"
  },
  {
    "id": "626",
    "name": "NihiL"
  },
  {
    "id": "627",
    "name": "[STLK] Ashasin"
  },
  {
    "id": "628",
    "name": "l3oux"
  },
  {
    "id": "629",
    "name": "[STLK] Xhaox"
  },
  {
    "id": "630",
    "name": "[BTK] Koresten"
  },
  {
    "id": "631",
    "name": "Plouf"
  },
  {
    "id": "632",
    "name": "Charles Blackwell"
  },
  {
    "id": "633",
    "name": "Kh@bib"
  },
  {
    "id": "634",
    "name": "Seydger"
  },
  {
    "id": "635",
    "name": "Bluth"
  },
  {
    "id": "636",
    "name": "Mtb.Biestro-KGSap"
  },
  {
    "id": "637",
    "name": "Smm.Roelandt-QGCmd"
  },
  {
    "id": "638",
    "name": "Emil"
  },
  {
    "id": "639",
    "name": "Cyril"
  },
  {
    "id": "640",
    "name": "YaC"
  },
  {
    "id": "641",
    "name": "hyrodes"
  },
  {
    "id": "642",
    "name": "Matzada"
  },
  {
    "id": "643",
    "name": "Tygeradan"
  },
  {
    "id": "644",
    "name": "Gatou"
  },
  {
    "id": "645",
    "name": "donald"
  },
  {
    "id": "646",
    "name": "Maex Wiemaen"
  },
  {
    "id": "647",
    "name": "Baros K."
  },
  {
    "id": "648",
    "name": "amrhe"
  },
  {
    "id": "649",
    "name": "J. Craw"
  },
  {
    "id": "650",
    "name": "Max"
  },
  {
    "id": "651",
    "name": "=S.O.F=Flash-Ranger"
  },
  {
    "id": "652",
    "name": "Mtl.Picou-QGPil"
  },
  {
    "id": "653",
    "name": "David J. Foster"
  },
  {
    "id": "654",
    "name": "[1er R.C.C] Nymon"
  },
  {
    "id": "655",
    "name": "UNThatPlaysForHonor"
  },
  {
    "id": "656",
    "name": "Skyonline123"
  },
  {
    "id": "657",
    "name": "CPL. Jenkins"
  },
  {
    "id": "658",
    "name": "Tyra"
  },
  {
    "id": "659",
    "name": "[IFA3]DMorok"
  },
  {
    "id": "660",
    "name": "Louis"
  },
  {
    "id": "661",
    "name": "*Stardust*"
  },
  {
    "id": "662",
    "name": "GSTAVO"
  },
  {
    "id": "663",
    "name": "[IFA3] iron_excelsior"
  },
  {
    "id": "664",
    "name": "[IFA3] Lawz"
  },
  {
    "id": "665",
    "name": "Hugin"
  },
  {
    "id": "666",
    "name": "Mp.Ohliger-1Cmd"
  },
  {
    "id": "667",
    "name": "Qm2.Maler-8Vol"
  },
  {
    "id": "669",
    "name": "Qm2.Neven-8Inf"
  },
  {
    "id": "672",
    "name": "PokheaD"
  },
  {
    "id": "673",
    "name": "Maex Wieman"
  },
  {
    "id": "674",
    "name": "[ANVIL] Spoks"
  },
  {
    "id": "675",
    "name": "[ANVIL] ArtemTM"
  },
  {
    "id": "676",
    "name": "[ANVIL] Ackerman"
  },
  {
    "id": "677",
    "name": "Owl"
  },
  {
    "id": "678",
    "name": "[ANVIL] FIRESTARTER"
  },
  {
    "id": "679",
    "name": "[RATS]Hannibal"
  },
  {
    "id": "680",
    "name": "[ANVIL] Markus"
  },
  {
    "id": "681",
    "name": "[IMB]PIONEER"
  },
  {
    "id": "682",
    "name": "[OLD]Gizmo"
  },
  {
    "id": "683",
    "name": "Laikom"
  },
  {
    "id": "684",
    "name": "[OLD]santa"
  },
  {
    "id": "686",
    "name": "[OLD]Ural"
  },
  {
    "id": "687",
    "name": "[IMB]Dalnoboi"
  },
  {
    "id": "688",
    "name": "[StB]Barmaglot"
  },
  {
    "id": "689",
    "name": "Donut"
  },
  {
    "id": "690",
    "name": "Darkmirror"
  },
  {
    "id": "691",
    "name": "legcs"
  },
  {
    "id": "692",
    "name": "Gabi 3x"
  },
  {
    "id": "693",
    "name": "Bobbyte"
  },
  {
    "id": "694",
    "name": "Pretorus"
  },
  {
    "id": "695",
    "name": "Oups"
  },
  {
    "id": "696",
    "name": "Mtb.Picou-QGPil"
  },
  {
    "id": "697",
    "name": "Mtb.Richen-1Lav"
  },
  {
    "id": "698",
    "name": "Mtb.Faure-8Lav"
  },
  {
    "id": "699",
    "name": "Tpr. T. Falkland"
  },
  {
    "id": "700",
    "name": "JewJew"
  },
  {
    "id": "701",
    "name": "ilbinek"
  },
  {
    "id": "702",
    "name": "Hydra"
  },
  {
    "id": "703",
    "name": "[BWB]Bobbyte"
  },
  {
    "id": "704",
    "name": "Miguelito.E"
  },
  {
    "id": "705",
    "name": "demio"
  },
  {
    "id": "706",
    "name": "Qm2.De Naurois.1Sap"
  },
  {
    "id": "707",
    "name": "Maj.Labas-QGCmd"
  },
  {
    "id": "708",
    "name": "[1er R.C.C] Malarkey"
  },
  {
    "id": "709",
    "name": "[1er R.C.C] Sharp"
  },
  {
    "id": "710",
    "name": "PheNoMiX"
  },
  {
    "id": "712",
    "name": "[ANVIL] Kpoji4er"
  },
  {
    "id": "713",
    "name": "[RATS]ARAB"
  },
  {
    "id": "714",
    "name": "Arn"
  },
  {
    "id": "715",
    "name": "[TNA] Cybernetik"
  },
  {
    "id": "716",
    "name": "[TNA] Waldemar"
  },
  {
    "id": "717",
    "name": "[StB]Forester"
  },
  {
    "id": "718",
    "name": "[TNA] 6oTer"
  },
  {
    "id": "719",
    "name": "Rieper"
  },
  {
    "id": "720",
    "name": "Rudolf Markush (endless"
  },
  {
    "id": "721",
    "name": "Piraten"
  },
  {
    "id": "722",
    "name": "Paul Hessel (Berigz"
  },
  {
    "id": "723",
    "name": "Adolf Eichmann"
  },
  {
    "id": "724",
    "name": "Davaulker"
  },
  {
    "id": "725",
    "name": "Rahm Stein"
  },
  {
    "id": "726",
    "name": "Bastien Carter"
  },
  {
    "id": "727",
    "name": "Rhal"
  },
  {
    "id": "728",
    "name": "Hans Muller"
  },
  {
    "id": "729",
    "name": "[ZHAC]ZMAK"
  },
  {
    "id": "730",
    "name": "[ZHAC]Lord"
  },
  {
    "id": "731",
    "name": "[ZHAC]DrJekyll"
  },
  {
    "id": "732",
    "name": "[FRWL] ZAMPOLIT"
  },
  {
    "id": "733",
    "name": "[ZHAC]spYros"
  },
  {
    "id": "734",
    "name": "[ZHAC]Airborner"
  },
  {
    "id": "735",
    "name": "[ANVIL] Area"
  },
  {
    "id": "736",
    "name": "DEA Agent Javier Peña"
  },
  {
    "id": "737",
    "name": "DEA _Agent_Steve_Murphy"
  },
  {
    "id": "738",
    "name": "Mtl.Nicot-8Stn"
  },
  {
    "id": "739",
    "name": "Oblongos"
  },
  {
    "id": "740",
    "name": "endless1506"
  },
  {
    "id": "741",
    "name": "Caliako Yukigari"
  },
  {
    "id": "742",
    "name": "Novalpro"
  },
  {
    "id": "743",
    "name": "Ray"
  },
  {
    "id": "744",
    "name": "Guitoplay"
  },
  {
    "id": "745",
    "name": "Oblong"
  },
  {
    "id": "746",
    "name": "Baban38"
  },
  {
    "id": "747",
    "name": "[MOR] Devildog"
  },
  {
    "id": "748",
    "name": "Sam"
  },
  {
    "id": "749",
    "name": "Leonardo da 13"
  },
  {
    "id": "750",
    "name": "Forza JewJewFerarri"
  },
  {
    "id": "751",
    "name": "J. Alton Alfalan"
  },
  {
    "id": "752",
    "name": "Qm2.Picou-QGPil"
  },
  {
    "id": "753",
    "name": "Sm2.Roelandt-QGCmd"
  },
  {
    "id": "754",
    "name": "Axel"
  },
  {
    "id": "755",
    "name": "[19th] Comrade Pilot"
  },
  {
    "id": "756",
    "name": "Cpl. Fisk"
  },
  {
    "id": "757",
    "name": "OStGefr. Magnoraider"
  },
  {
    "id": "758",
    "name": "[MOR] Ramiel"
  },
  {
    "id": "759",
    "name": "unr3al"
  },
  {
    "id": "760",
    "name": "Magmaul"
  },
  {
    "id": "761",
    "name": "Hansi Sheep"
  },
  {
    "id": "762",
    "name": "BadBoy"
  },
  {
    "id": "763",
    "name": "BuboSK"
  },
  {
    "id": "764",
    "name": "M4rtell0"
  },
  {
    "id": "765",
    "name": "PikachuCake"
  },
  {
    "id": "767",
    "name": "Countermatt"
  },
  {
    "id": "768",
    "name": "László"
  },
  {
    "id": "769",
    "name": "Amnez"
  },
  {
    "id": "770",
    "name": "Nico"
  },
  {
    "id": "771",
    "name": "[OFrP]Bastien Carter"
  },
  {
    "id": "772",
    "name": "[TrES] Geronimo Röder"
  },
  {
    "id": "773",
    "name": "Alekanderu"
  },
  {
    "id": "774",
    "name": "Nickyinsanity"
  },
  {
    "id": "775",
    "name": "Forrer"
  },
  {
    "id": "776",
    "name": "Dahlgren"
  },
  {
    "id": "777",
    "name": "xealot"
  },
  {
    "id": "778",
    "name": "Metro"
  },
  {
    "id": "779",
    "name": "Mpenga"
  },
  {
    "id": "780",
    "name": "Stefan"
  },
  {
    "id": "781",
    "name": "sillburk"
  },
  {
    "id": "782",
    "name": "vinds"
  },
  {
    "id": "783",
    "name": "BanAzze"
  },
  {
    "id": "784",
    "name": "Snakevsocelot"
  },
  {
    "id": "785",
    "name": "Rico."
  },
  {
    "id": "786",
    "name": "Roxsore"
  },
  {
    "id": "787",
    "name": "#REF !"
  },
  {
    "id": "789",
    "name": "[PHX] Nick"
  },
  {
    "id": "790",
    "name": "[PHX] Lujan"
  },
  {
    "id": "792",
    "name": "[PHX] Punisher"
  },
  {
    "id": "793",
    "name": "[PHX] TheBeast"
  },
  {
    "id": "794",
    "name": "[PHX] Finndu"
  },
  {
    "id": "795",
    "name": "Jonathan"
  },
  {
    "id": "796",
    "name": "DEA_Agent_Steve_Murphy"
  },
  {
    "id": "797",
    "name": "[1CL]Jonathan"
  },
  {
    "id": "798",
    "name": "TicTac"
  },
  {
    "id": "799",
    "name": "Mtb.Monceau-1Inf"
  },
  {
    "id": "800",
    "name": "Totem"
  },
  {
    "id": "802",
    "name": "SkarX"
  },
  {
    "id": "803",
    "name": "Col. Gibbo"
  },
  {
    "id": "804",
    "name": "OCdt. Sayon"
  },
  {
    "id": "805",
    "name": "LtCol. Zamok"
  },
  {
    "id": "806",
    "name": "MetalShock"
  },
  {
    "id": "807",
    "name": "[1er R.C.C] Axel"
  },
  {
    "id": "808",
    "name": "Qm1.Vinat-8Inf"
  },
  {
    "id": "809",
    "name": "Azenor"
  },
  {
    "id": "810",
    "name": "[FoS]MaDZerG"
  },
  {
    "id": "811",
    "name": "[UNT] Rageded"
  },
  {
    "id": "812",
    "name": "Ficelle"
  },
  {
    "id": "813",
    "name": "City"
  },
  {
    "id": "814",
    "name": "2RGT Sipo"
  },
  {
    "id": "815",
    "name": "pablo"
  },
  {
    "id": "816",
    "name": "[1er R.C.C] Kim-Jong-Pa"
  },
  {
    "id": "817",
    "name": "2RGT Pinza"
  },
  {
    "id": "818",
    "name": "CSF_Pacca"
  },
  {
    "id": "819",
    "name": "Furi"
  },
  {
    "id": "820",
    "name": "martysp"
  },
  {
    "id": "821",
    "name": "Black"
  },
  {
    "id": "822",
    "name": "Waschko"
  },
  {
    "id": "823",
    "name": "Prophet [OFCRA]"
  },
  {
    "id": "824",
    "name": "Crimson"
  },
  {
    "id": "825",
    "name": "TheVeverka"
  },
  {
    "id": "826",
    "name": "AssassinS Creed"
  },
  {
    "id": "827",
    "name": "[1er R.C.C] Lucas Wood"
  },
  {
    "id": "829",
    "name": "Kant1"
  },
  {
    "id": "831",
    "name": "|ToK|Oggy"
  },
  {
    "id": "832",
    "name": "|ToK| Kaan"
  },
  {
    "id": "833",
    "name": "Mtb.Nicot-8Stn"
  },
  {
    "id": "834",
    "name": "Skull"
  },
  {
    "id": "835",
    "name": "bot_41"
  },
  {
    "id": "836",
    "name": "Aleksander Wojtek"
  },
  {
    "id": "838",
    "name": "2Lt. N. Barden"
  },
  {
    "id": "839",
    "name": "Herobrain888"
  },
  {
    "id": "840",
    "name": "PissedoffGuy"
  },
  {
    "id": "841",
    "name": "|ToK|Talip"
  },
  {
    "id": "842",
    "name": "Norse_Harold"
  },
  {
    "id": "843",
    "name": "S/Sgt. M. Bluebeard"
  },
  {
    "id": "844",
    "name": "Pvt. T. Kazansky"
  },
  {
    "id": "845",
    "name": "Cpl. D. Christ"
  },
  {
    "id": "846",
    "name": "A/LCpl. B. Powell"
  },
  {
    "id": "847",
    "name": "A/Bdr. M. Shardonia"
  },
  {
    "id": "848",
    "name": "A/Sgt. A. Baz"
  },
  {
    "id": "849",
    "name": "PVT. C. Ackerman"
  },
  {
    "id": "850",
    "name": "Theretor"
  },
  {
    "id": "851",
    "name": "Delaney [19th]"
  },
  {
    "id": "852",
    "name": "omL"
  },
  {
    "id": "853",
    "name": "Arkion"
  },
  {
    "id": "856",
    "name": "Dontoto"
  },
  {
    "id": "857",
    "name": "2RGT Refiston_"
  },
  {
    "id": "859",
    "name": "Voold"
  },
  {
    "id": "860",
    "name": "Keenan"
  },
  {
    "id": "861",
    "name": "[PHX] KarbineR"
  },
  {
    "id": "862",
    "name": "Nick"
  },
  {
    "id": "863",
    "name": "|ToK|Orhun"
  },
  {
    "id": "864",
    "name": "[6eme BAP] Shadow"
  },
  {
    "id": "865",
    "name": "[6eme BAP] Clement"
  },
  {
    "id": "866",
    "name": "Jatha"
  },
  {
    "id": "867",
    "name": "Izidore"
  },
  {
    "id": "868",
    "name": "BorderKeeper"
  },
  {
    "id": "869",
    "name": "TheSpaceDwarf"
  },
  {
    "id": "870",
    "name": "Chyper1"
  },
  {
    "id": "871",
    "name": "Perpetual"
  },
  {
    "id": "872",
    "name": "Viking18"
  },
  {
    "id": "873",
    "name": "Cyclo"
  },
  {
    "id": "874",
    "name": "Bizo"
  },
  {
    "id": "875",
    "name": "LUCAS"
  },
  {
    "id": "876",
    "name": "Ronnie21093"
  },
  {
    "id": "877",
    "name": "Dora"
  },
  {
    "id": "878",
    "name": "Noel"
  },
  {
    "id": "879",
    "name": "Little_scot"
  },
  {
    "id": "880",
    "name": "Mtl.Salaün-QGZeus"
  },
  {
    "id": "881",
    "name": "Qm2.Maler-8Lav"
  },
  {
    "id": "882",
    "name": "Qm2.Picou-QGPlt"
  },
  {
    "id": "883",
    "name": "P4sc4l"
  },
  {
    "id": "884",
    "name": "CSF_Mat"
  },
  {
    "id": "885",
    "name": "999danny"
  },
  {
    "id": "886",
    "name": "Webber"
  },
  {
    "id": "887",
    "name": "[1er R.C.C] Dontoto"
  },
  {
    "id": "888",
    "name": "CSF_Melt"
  },
  {
    "id": "889",
    "name": "Angelo"
  },
  {
    "id": "890",
    "name": "2RGT"
  },
  {
    "id": "891",
    "name": "Mtl.Salaün-QGFsl"
  },
  {
    "id": "892",
    "name": "NotADoctor"
  },
  {
    "id": "893",
    "name": "[6eme BAP] Zakarov"
  },
  {
    "id": "894",
    "name": "2RGT (2"
  },
  {
    "id": "896",
    "name": "Antrax"
  },
  {
    "id": "897",
    "name": "[1er R.C.C] Bernard"
  },
  {
    "id": "898",
    "name": "Redhotita1"
  },
  {
    "id": "899",
    "name": "Hawke"
  },
  {
    "id": "900",
    "name": "2RGT INFINITY117"
  },
  {
    "id": "901",
    "name": "Fenice319"
  },
  {
    "id": "902",
    "name": "bibobabo"
  },
  {
    "id": "903",
    "name": "2RGT_Neon"
  },
  {
    "id": "904",
    "name": "MigFulcrum"
  },
  {
    "id": "905",
    "name": "Garry"
  },
  {
    "id": "906",
    "name": "Darth Ross"
  },
  {
    "id": "907",
    "name": "Gilatar"
  },
  {
    "id": "908",
    "name": "Cadet.Gouriou-8Fsl"
  },
  {
    "id": "909",
    "name": "DEA_Agent_Murphy"
  },
  {
    "id": "910",
    "name": "19th [Goose]"
  },
  {
    "id": "911",
    "name": "Maverick"
  },
  {
    "id": "912",
    "name": "PFC J.Landa"
  },
  {
    "id": "913",
    "name": "[MOR] MIKI"
  },
  {
    "id": "914",
    "name": "[MOR] Hall"
  },
  {
    "id": "915",
    "name": "[6eme BAP] Clem's"
  },
  {
    "id": "916",
    "name": "RoyDeCamper3"
  },
  {
    "id": "917",
    "name": "Zecatch"
  },
  {
    "id": "918",
    "name": "Commissar Parthius"
  },
  {
    "id": "919",
    "name": "Guardsman Parthius"
  },
  {
    "id": "920",
    "name": "[6eme BAP] Totonben"
  },
  {
    "id": "921",
    "name": "Johann Schnitter"
  },
  {
    "id": "922",
    "name": "Enginseer Parthius"
  },
  {
    "id": "924",
    "name": "CSF_Eko"
  },
  {
    "id": "925",
    "name": "[6emeBAP] ToTonben"
  },
  {
    "id": "926",
    "name": "[6eme BAP] Giien"
  },
  {
    "id": "927",
    "name": "Sparfell"
  },
  {
    "id": "928",
    "name": "[6eme BAP] Jack Oneill"
  },
  {
    "id": "929",
    "name": "[6eme BAP] LeO_"
  },
  {
    "id": "930",
    "name": "ToastSmack"
  },
  {
    "id": "931",
    "name": "TheoTheGril"
  },
  {
    "id": "932",
    "name": "merdy"
  },
  {
    "id": "933",
    "name": "HazardousChurch"
  },
  {
    "id": "934",
    "name": "[MOR] Rasty69"
  },
  {
    "id": "935",
    "name": "Piecemaker_187"
  },
  {
    "id": "936",
    "name": "Emperias"
  },
  {
    "id": "937",
    "name": "Bulletproof_187"
  },
  {
    "id": "938",
    "name": "juju"
  },
  {
    "id": "939",
    "name": "[1er R.C.C] Florian"
  },
  {
    "id": "940",
    "name": "CSF_David"
  },
  {
    "id": "942",
    "name": "DirtyHenry"
  },
  {
    "id": "943",
    "name": "Warzen"
  },
  {
    "id": "944",
    "name": "Mystery"
  },
  {
    "id": "945",
    "name": "Sardo"
  },
  {
    "id": "946",
    "name": "Guy that shoots bad guys"
  },
  {
    "id": "947",
    "name": "TheMasterofBlubb"
  },
  {
    "id": "948",
    "name": "Rigel"
  },
  {
    "id": "949",
    "name": "Fonzy19"
  },
  {
    "id": "950",
    "name": "[1er R.C.C] Dypra"
  },
  {
    "id": "951",
    "name": "Tirette"
  },
  {
    "id": "952",
    "name": "Launi"
  },
  {
    "id": "953",
    "name": "Pleace"
  },
  {
    "id": "954",
    "name": "Cesio"
  },
  {
    "id": "955",
    "name": "Lux"
  },
  {
    "id": "956",
    "name": "Saiko"
  },
  {
    "id": "957",
    "name": "Thunder"
  },
  {
    "id": "958",
    "name": "Sipo"
  },
  {
    "id": "959",
    "name": "CSF_Corvo"
  },
  {
    "id": "960",
    "name": "The sniper"
  },
  {
    "id": "961",
    "name": "Anam"
  },
  {
    "id": "962",
    "name": "Sirius"
  },
  {
    "id": "963",
    "name": "BobWinchester"
  },
  {
    "id": "964",
    "name": "[1er R.C.C] Blackstorm"
  },
  {
    "id": "965",
    "name": "Mtl.Rollin-8Inf"
  },
  {
    "id": "966",
    "name": "Mtl.Archieri-QGFsl"
  },
  {
    "id": "967",
    "name": "[CTU] Meme"
  },
  {
    "id": "968",
    "name": "[CTU]carlos-r95"
  },
  {
    "id": "969",
    "name": "|ToK| Alper"
  },
  {
    "id": "970",
    "name": "Shooter"
  },
  {
    "id": "971",
    "name": "Zombi"
  },
  {
    "id": "972",
    "name": "Rihter"
  },
  {
    "id": "973",
    "name": "Alex_D20"
  },
  {
    "id": "974",
    "name": "[TRD]Plague_DoctorUA"
  },
  {
    "id": "975",
    "name": "[TRD] Yurko_Poker"
  },
  {
    "id": "976",
    "name": "[TRD]SvaroG"
  },
  {
    "id": "977",
    "name": "Kozac"
  },
  {
    "id": "978",
    "name": "??????"
  },
  {
    "id": "979",
    "name": "Igor"
  },
  {
    "id": "981",
    "name": "????"
  },
  {
    "id": "982",
    "name": "Lazar"
  },
  {
    "id": "985",
    "name": "Tarmak"
  },
  {
    "id": "986",
    "name": "larcenn"
  },
  {
    "id": "987",
    "name": "galevsky"
  },
  {
    "id": "988",
    "name": "BLANKETOU"
  },
  {
    "id": "989",
    "name": "Pix"
  },
  {
    "id": "990",
    "name": "Ketraies"
  },
  {
    "id": "991",
    "name": "MrChy"
  },
  {
    "id": "992",
    "name": "Loccky"
  },
  {
    "id": "993",
    "name": "[1er R.C.C] Gabriel"
  },
  {
    "id": "994",
    "name": "Amygagaz-"
  },
  {
    "id": "995",
    "name": "Always"
  },
  {
    "id": "996",
    "name": "Saverass"
  },
  {
    "id": "997",
    "name": "arcuce"
  },
  {
    "id": "998",
    "name": "Azrel"
  },
  {
    "id": "999",
    "name": "[TRD] Rihter"
  },
  {
    "id": "1000",
    "name": "[TRD]Mopnex"
  },
  {
    "id": "1001",
    "name": "[TRD]Vinni4anin"
  },
  {
    "id": "1002",
    "name": "[TRD]~Black_Wolf~"
  },
  {
    "id": "1003",
    "name": "[TRD] Samiylo_Kishka"
  },
  {
    "id": "1004",
    "name": "[TRD]AvAlon"
  },
  {
    "id": "1005",
    "name": "[L-13]Mattoni"
  },
  {
    "id": "1006",
    "name": "[CTU] Niko90"
  },
  {
    "id": "1007",
    "name": "SnakeDoctorLT"
  },
  {
    "id": "1008",
    "name": "DiGaruu"
  },
  {
    "id": "1009",
    "name": "|ToK| KN"
  },
  {
    "id": "1010",
    "name": "|ToK|ottoTR"
  },
  {
    "id": "1011",
    "name": "|ToK| Broklins"
  },
  {
    "id": "1012",
    "name": "Karahilal"
  },
  {
    "id": "1013",
    "name": "Albert Roche"
  },
  {
    "id": "1014",
    "name": "Stryker Wildfire"
  },
  {
    "id": "1015",
    "name": "[MOR] Sixor"
  },
  {
    "id": "1016",
    "name": "[6eme BAP] Loick"
  },
  {
    "id": "1017",
    "name": "[6ème BAP] Pa-Chi-Minh"
  },
  {
    "id": "1018",
    "name": "[SWAG] Max Weeman"
  },
  {
    "id": "1019",
    "name": "[TRD]Nakpena"
  },
  {
    "id": "1020",
    "name": "Crni"
  },
  {
    "id": "1021",
    "name": "Luka"
  },
  {
    "id": "1022",
    "name": "?????"
  },
  {
    "id": "1023",
    "name": "[CK] Dechamboux Fsl"
  },
  {
    "id": "1024",
    "name": "Qm1.Gadou-2Ast"
  },
  {
    "id": "1025",
    "name": "[1er R.C.C] Hadrien"
  },
  {
    "id": "1026",
    "name": "[1er R.C.C] Romain"
  },
  {
    "id": "1028",
    "name": "Sm1.Dechamboux -KGCmd"
  },
  {
    "id": "1029",
    "name": "Karl Konnor"
  },
  {
    "id": "1030",
    "name": "Zed"
  },
  {
    "id": "1031",
    "name": "ilpepi87"
  },
  {
    "id": "1032",
    "name": "CSF_Simone"
  },
  {
    "id": "1033",
    "name": "0"
  },
  {
    "id": "1034",
    "name": "HawKz"
  },
  {
    "id": "1035",
    "name": "Tarik"
  },
  {
    "id": "1036",
    "name": "Slin khadim"
  },
  {
    "id": "1038",
    "name": "[TRD] Tikara"
  },
  {
    "id": "1039",
    "name": "[TRD]lvivskixlop"
  },
  {
    "id": "1042",
    "name": "warome"
  },
  {
    "id": "1043",
    "name": "[1er R.C.C] Ice"
  },
  {
    "id": "1044",
    "name": "[1er R.C.C] Pablo Mugabe"
  },
  {
    "id": "1045",
    "name": "[1er R.C.C] Tirette"
  },
  {
    "id": "1046",
    "name": "[1er R.C.C] Pickles_Kim"
  },
  {
    "id": "1047",
    "name": "Pm.Le Rigoleur-1Cmd"
  },
  {
    "id": "1048",
    "name": "Mtl.Moguerou-KGFsl"
  },
  {
    "id": "1049",
    "name": "Mtl.Rollin-KGInf"
  },
  {
    "id": "1050",
    "name": "Sm1.Dechamboux - KGCmd"
  },
  {
    "id": "1051",
    "name": "[6eme BAP] Urzuglu"
  },
  {
    "id": "1052",
    "name": "John"
  },
  {
    "id": "1053",
    "name": "Niko"
  },
  {
    "id": "1054",
    "name": "CSF_Gigim"
  },
  {
    "id": "1055",
    "name": "CSF_Shyrowaza"
  },
  {
    "id": "1056",
    "name": "[ToK]Azazilll"
  },
  {
    "id": "1057",
    "name": "rowet"
  },
  {
    "id": "1058",
    "name": "Atle Morten"
  },
  {
    "id": "1059",
    "name": "[1er R.C.C] Skip"
  },
  {
    "id": "1060",
    "name": "Ev1.Massin-QGCmd"
  },
  {
    "id": "1061",
    "name": "CSF_Furia"
  },
  {
    "id": "1062",
    "name": "CSF_Narco"
  },
  {
    "id": "1063",
    "name": "Marx Unsermann"
  },
  {
    "id": "1064",
    "name": "Herr Bodewig"
  },
  {
    "id": "1065",
    "name": "2nd Lt. C. McHellsten"
  },
  {
    "id": "1066",
    "name": "Cpl. E. Hood"
  },
  {
    "id": "1067",
    "name": "PV2 E. Wedgeworth"
  },
  {
    "id": "1069",
    "name": "WOC P. Guy"
  },
  {
    "id": "1070",
    "name": "Sgt. N. Shoffner"
  },
  {
    "id": "1071",
    "name": "[6eme BAP] Feldm"
  },
  {
    "id": "1072",
    "name": "[TRD] Syr"
  },
  {
    "id": "1073",
    "name": "lon4ik03"
  },
  {
    "id": "1074",
    "name": "|ToK|KemalUrhan"
  },
  {
    "id": "1075",
    "name": "CPL C. Jandreau"
  },
  {
    "id": "1076",
    "name": "Lt. Steel"
  },
  {
    "id": "1077",
    "name": "Cadet.Gouriou-Fsl"
  },
  {
    "id": "1078",
    "name": "[6eme BAP] Exoduko"
  },
  {
    "id": "1079",
    "name": "Rikysav"
  },
  {
    "id": "1080",
    "name": "Cheeseburger"
  },
  {
    "id": "1081",
    "name": "Swede"
  },
  {
    "id": "1082",
    "name": "Archaeon"
  },
  {
    "id": "1083",
    "name": "rund"
  },
  {
    "id": "1084",
    "name": "Ekstranden"
  },
  {
    "id": "1085",
    "name": "Bestefar"
  },
  {
    "id": "1086",
    "name": "LucyL"
  },
  {
    "id": "1087",
    "name": "Loffa"
  },
  {
    "id": "1088",
    "name": "Skalman"
  },
  {
    "id": "1089",
    "name": "[1er R.C.C] Forxtop"
  },
  {
    "id": "1090",
    "name": "Adri"
  },
  {
    "id": "1091",
    "name": "R8TeD"
  },
  {
    "id": "1092",
    "name": "Vort"
  },
  {
    "id": "1093",
    "name": "Andreas"
  },
  {
    "id": "1094",
    "name": "Lt. S. Chair"
  },
  {
    "id": "1095",
    "name": "[TTC]Emperor"
  },
  {
    "id": "1096",
    "name": "North"
  },
  {
    "id": "1099",
    "name": "[TRD]SiM"
  },
  {
    "id": "1100",
    "name": "[TRD] Mr. Jack"
  },
  {
    "id": "1101",
    "name": "[1er R.C.C] Charles"
  },
  {
    "id": "1102",
    "name": "[TRD]lon4ik03"
  },
  {
    "id": "1103",
    "name": "PVT C. Espinoza"
  },
  {
    "id": "1104",
    "name": "Cpl. P. Andersson"
  },
  {
    "id": "1106",
    "name": "L. Zappkorvski"
  },
  {
    "id": "1107",
    "name": "LordShade"
  },
  {
    "id": "1108",
    "name": "varrkan_ua"
  },
  {
    "id": "1109",
    "name": "taras"
  },
  {
    "id": "1110",
    "name": "[UKAZ]Barmalei"
  },
  {
    "id": "1111",
    "name": "[UkAZ]SHTURM_1973"
  },
  {
    "id": "1112",
    "name": "[UkAZ]Savos"
  },
  {
    "id": "1113",
    "name": "thehunterdk"
  },
  {
    "id": "1114",
    "name": "Pte. L. Menin"
  },
  {
    "id": "1115",
    "name": "[CTU] Meme."
  },
  {
    "id": "1116",
    "name": "KOLOOLOO"
  },
  {
    "id": "1117",
    "name": "A/LCpl. J. Grange"
  },
  {
    "id": "1118",
    "name": "Cpl. C. Thorpe"
  },
  {
    "id": "1119",
    "name": "2Lt. D. Thire"
  },
  {
    "id": "1120",
    "name": "Pte. T. Fisher"
  },
  {
    "id": "1121",
    "name": "Pte. G. Robertson"
  },
  {
    "id": "1122",
    "name": "Pte. M. Potter"
  },
  {
    "id": "1123",
    "name": "acog"
  },
  {
    "id": "1124",
    "name": "[MUNJE]Vuk"
  },
  {
    "id": "1125",
    "name": "[Munje]Aleksandar"
  },
  {
    "id": "1126",
    "name": "SSG. Kaish"
  },
  {
    "id": "1127",
    "name": "[MUNJE] Scharke"
  },
  {
    "id": "1128",
    "name": "Munje|Topic"
  },
  {
    "id": "1129",
    "name": "Pte. A. Baz"
  },
  {
    "id": "1130",
    "name": "Cpl. F. Stangenberger"
  },
  {
    "id": "1131",
    "name": "Pte. P. Valli"
  },
  {
    "id": "1132",
    "name": "Pte. N. Monahan"
  },
  {
    "id": "1133",
    "name": "Cpl. M. Standish"
  },
  {
    "id": "1134",
    "name": "[StB]Termitok"
  },
  {
    "id": "1135",
    "name": "CSF_Messeno"
  },
  {
    "id": "1136",
    "name": "Pte. Rendo"
  },
  {
    "id": "1137",
    "name": "denhatter"
  },
  {
    "id": "1138",
    "name": "[UkAZ]Warkas"
  },
  {
    "id": "1139",
    "name": "[1er R.C.C] Warome"
  },
  {
    "id": "1140",
    "name": "Pte. C. Reichert"
  },
  {
    "id": "1141",
    "name": "Pte. A. Morin"
  },
  {
    "id": "1142",
    "name": "Pte. M. Bluebeard"
  },
  {
    "id": "1143",
    "name": "Pte. J. Laurent"
  },
  {
    "id": "1144",
    "name": "Pte. Y. Ignatov"
  },
  {
    "id": "1145",
    "name": "Corto Maltese"
  },
  {
    "id": "1146",
    "name": "LCpl. C. Knight"
  },
  {
    "id": "1147",
    "name": "Vindsnabb"
  },
  {
    "id": "1148",
    "name": "Valdas"
  },
  {
    "id": "1149",
    "name": "SomeNorGuy"
  },
  {
    "id": "1150",
    "name": "Mtb.Rollin - KGinf"
  },
  {
    "id": "1151",
    "name": "Mtb.Maler-1Fsl"
  },
  {
    "id": "1152",
    "name": "Mtb.Archieri-QGFsl"
  },
  {
    "id": "1153",
    "name": "Mtl.Gouriou-KgFsl"
  },
  {
    "id": "1154",
    "name": "|UN|Sgt.Vlad"
  },
  {
    "id": "1155",
    "name": "JoelBitar"
  },
  {
    "id": "1156",
    "name": "Tackle"
  },
  {
    "id": "1157",
    "name": "CyDoN"
  },
  {
    "id": "1158",
    "name": "Slav Vador"
  },
  {
    "id": "1159",
    "name": "L0r4n"
  },
  {
    "id": "1160",
    "name": "Odin Cannabis"
  },
  {
    "id": "1161",
    "name": "RazKa"
  },
  {
    "id": "1162",
    "name": "Otto von Bigmac"
  },
  {
    "id": "1163",
    "name": "Lt.Klingman (djazore)"
  },
  {
    "id": "1164",
    "name": "Cpl McLaren (Sauron)"
  },
  {
    "id": "1165",
    "name": "Popeye"
  },
  {
    "id": "1166",
    "name": "[TON] Vauban (Aigle2)"
  },
  {
    "id": "1167",
    "name": "Leonessa84"
  },
  {
    "id": "1168",
    "name": "Melt"
  },
  {
    "id": "1169",
    "name": "TastyFettuccine"
  },
  {
    "id": "1170",
    "name": "Blade"
  },
  {
    "id": "1171",
    "name": "[SIG] 999danny"
  },
  {
    "id": "1172",
    "name": "carioca"
  },
  {
    "id": "1173",
    "name": "kimi"
  },
  {
    "id": "1174",
    "name": "[5TH AR] OF-4. Dawson X"
  },
  {
    "id": "1175",
    "name": "[5th]Kofee"
  },
  {
    "id": "1176",
    "name": "[6eme BAP] Otoko"
  },
  {
    "id": "1177",
    "name": "Ärrow"
  },
  {
    "id": "1178",
    "name": "Gonzo"
  },
  {
    "id": "1179",
    "name": "[SIG] Tokyo (Nick)"
  },
  {
    "id": "1180",
    "name": "čet. NOMAD"
  },
  {
    "id": "1181",
    "name": "Chicago"
  },
  {
    "id": "1182",
    "name": "Zerogravity"
  },
  {
    "id": "1183",
    "name": "CSF_Haplo"
  },
  {
    "id": "1184",
    "name": "CSF_Hunter"
  },
  {
    "id": "1185",
    "name": "Magnetar"
  },
  {
    "id": "1186",
    "name": "[Sargento] Kill Lixus"
  },
  {
    "id": "1187",
    "name": "[Teniente] RanTa"
  },
  {
    "id": "1188",
    "name": "[Sargento] Ari"
  },
  {
    "id": "1189",
    "name": "[Cabo] Incongo"
  },
  {
    "id": "1190",
    "name": "[Soldado] Nasso"
  },
  {
    "id": "1191",
    "name": "[Soldado] Rascarcio"
  },
  {
    "id": "1192",
    "name": "[Sargento] BigOdoX"
  },
  {
    "id": "1193",
    "name": "[Soldado 1ª] Awizor"
  },
  {
    "id": "1194",
    "name": "Lcpl. Liru"
  },
  {
    "id": "1195",
    "name": "Mad Max"
  },
  {
    "id": "1196",
    "name": "Sgt. D. Hovey"
  },
  {
    "id": "1197",
    "name": "Danne_Swede"
  },
  {
    "id": "1198",
    "name": "Kristo"
  },
  {
    "id": "1199",
    "name": "Sgt. Falcon"
  },
  {
    "id": "1200",
    "name": "Pte. Biscuit"
  },
  {
    "id": "1201",
    "name": "Pte. Ram"
  },
  {
    "id": "1202",
    "name": "[6eme BAP] Blake"
  },
  {
    "id": "1203",
    "name": "Cobra"
  },
  {
    "id": "1204",
    "name": "LCpl. Quinn"
  },
  {
    "id": "1205",
    "name": "[6ème BAP] ScaniaH"
  },
  {
    "id": "1206",
    "name": "[6eme BAP] Bocognano"
  },
  {
    "id": "1207",
    "name": "Pfc. E. McKinney"
  },
  {
    "id": "1208",
    "name": "Wintermoon"
  },
  {
    "id": "1209",
    "name": "LCpl. Clacker"
  },
  {
    "id": "1210",
    "name": "Pte. Mills"
  },
  {
    "id": "1211",
    "name": "Kubackiewicz"
  },
  {
    "id": "1212",
    "name": "Misza"
  },
  {
    "id": "1213",
    "name": "Luffy"
  },
  {
    "id": "1214",
    "name": "[TON] Complex"
  },
  {
    "id": "1215",
    "name": "[6eme BAP] Alex Ora"
  },
  {
    "id": "1216",
    "name": "Sir Nop"
  },
  {
    "id": "1217",
    "name": "Robinio"
  },
  {
    "id": "1218",
    "name": "Sgt. C. Anderson"
  },
  {
    "id": "1219",
    "name": "Kamiskub"
  },
  {
    "id": "1220",
    "name": "honger"
  },
  {
    "id": "1221",
    "name": "Ziemek"
  },
  {
    "id": "1222",
    "name": "okular"
  },
  {
    "id": "1223",
    "name": "MrBadGuy35"
  },
  {
    "id": "1224",
    "name": "[PV2] P.Setler"
  },
  {
    "id": "1225",
    "name": "ZIUM"
  },
  {
    "id": "1226",
    "name": "Jules"
  },
  {
    "id": "1227",
    "name": "DREED"
  },
  {
    "id": "1228",
    "name": "VATICAN PSYCHO"
  },
  {
    "id": "1229",
    "name": "Davidaf"
  },
  {
    "id": "1230",
    "name": "Monika"
  },
  {
    "id": "1231",
    "name": "Minos AI"
  },
  {
    "id": "1232",
    "name": "Carlitos"
  },
  {
    "id": "1233",
    "name": "Alphamyl"
  },
  {
    "id": "1234",
    "name": "Xente"
  },
  {
    "id": "1235",
    "name": "Funy Skywalker"
  },
  {
    "id": "1236",
    "name": "Angostad"
  },
  {
    "id": "1237",
    "name": "Liquid"
  },
  {
    "id": "1238",
    "name": "PasostanRamón"
  },
  {
    "id": "1239",
    "name": "Juan Calavera Calva"
  },
  {
    "id": "1240",
    "name": "[SIG]Lacedemone"
  },
  {
    "id": "1241",
    "name": "Malgrin"
  },
  {
    "id": "1242",
    "name": "Abey"
  },
  {
    "id": "1243",
    "name": "[PV2] A.Montana"
  },
  {
    "id": "1244",
    "name": "Adam"
  },
  {
    "id": "1245",
    "name": "Bart"
  },
  {
    "id": "1246",
    "name": "TFP"
  },
  {
    "id": "1247",
    "name": "Drago."
  },
  {
    "id": "1248",
    "name": "Dominik"
  },
  {
    "id": "1249",
    "name": "Kruko"
  },
  {
    "id": "1250",
    "name": "Sajgonka"
  },
  {
    "id": "1251",
    "name": "VeXenn"
  },
  {
    "id": "1252",
    "name": "Nowerian"
  },
  {
    "id": "1253",
    "name": "Kwas Acetylosalicylowy"
  },
  {
    "id": "1254",
    "name": "Jeremi."
  },
  {
    "id": "1255",
    "name": "Seal Willm"
  },
  {
    "id": "1256",
    "name": "JAFAR"
  },
  {
    "id": "1257",
    "name": "Cpl. C. A. Snakesmith"
  },
  {
    "id": "1258",
    "name": "[6eme BAP] Benioto"
  },
  {
    "id": "1259",
    "name": "MalmG"
  },
  {
    "id": "1260",
    "name": "43664"
  },
  {
    "id": "1261",
    "name": "Tric Trac"
  },
  {
    "id": "1262",
    "name": "Justicar"
  },
  {
    "id": "1263",
    "name": "=S.O.F=Nick"
  },
  {
    "id": "1264",
    "name": "Apap"
  },
  {
    "id": "1265",
    "name": "roxsa"
  },
  {
    "id": "1266",
    "name": "Barbascura"
  },
  {
    "id": "1267",
    "name": "Flender"
  },
  {
    "id": "1268",
    "name": "Feed Me Paper"
  },
  {
    "id": "1269",
    "name": "ff7712"
  },
  {
    "id": "1270",
    "name": "IceBreakr"
  },
  {
    "id": "1271",
    "name": "Spidi-[SBP]"
  },
  {
    "id": "1272",
    "name": "Zetho"
  },
  {
    "id": "1273",
    "name": "lordi"
  },
  {
    "id": "1274",
    "name": "Skipper"
  },
  {
    "id": "1275",
    "name": "MarshMelloGuy"
  },
  {
    "id": "1276",
    "name": "-FM-"
  },
  {
    "id": "1277",
    "name": "Worst"
  },
  {
    "id": "1278",
    "name": "Snoopy"
  },
  {
    "id": "1279",
    "name": "Muwafaq Salah Udin"
  },
  {
    "id": "1280",
    "name": "Uncl_Sam"
  },
  {
    "id": "1281",
    "name": "Genomas"
  },
  {
    "id": "1282",
    "name": "[Soldado 1ª] Alex"
  },
  {
    "id": "1283",
    "name": "[Soldado] Stark"
  },
  {
    "id": "1284",
    "name": "CSF_Bat"
  },
  {
    "id": "1285",
    "name": "[FJB49] Zed"
  },
  {
    "id": "1286",
    "name": "Pfc. D. Doyle"
  },
  {
    "id": "1287",
    "name": "Pzgren.Stadler.23PzD"
  },
  {
    "id": "1288",
    "name": "[StB]MEХBOD"
  },
  {
    "id": "1289",
    "name": "[StB]OPAHYC"
  },
  {
    "id": "1290",
    "name": "[StB]Hammer"
  },
  {
    "id": "1291",
    "name": "Dourdent"
  },
  {
    "id": "1292",
    "name": "Sdo1ª. Javi Bermejo"
  },
  {
    "id": "1293",
    "name": "Ghost"
  },
  {
    "id": "1294",
    "name": "Giorgio"
  },
  {
    "id": "1295",
    "name": "Szymekl"
  },
  {
    "id": "1296",
    "name": "ImFriendlyDino"
  },
  {
    "id": "1297",
    "name": "Mr.Squirrel"
  },
  {
    "id": "1298",
    "name": "Żegota Czarny III"
  },
  {
    "id": "1299",
    "name": "Ádám"
  },
  {
    "id": "1300",
    "name": "Shadow Stalker"
  },
  {
    "id": "1301",
    "name": "Gefr.Weiss.23PzD"
  },
  {
    "id": "1302",
    "name": "Pvt A. Osiadacz"
  },
  {
    "id": "1303",
    "name": "Gestapo"
  },
  {
    "id": "1304",
    "name": "[TRD] TIHAR"
  },
  {
    "id": "1305",
    "name": "[TRD]Soroka"
  },
  {
    "id": "1306",
    "name": "[TRD] teo"
  },
  {
    "id": "1307",
    "name": "Shay"
  },
  {
    "id": "1308",
    "name": "Dimitris"
  },
  {
    "id": "1309",
    "name": "Blee"
  },
  {
    "id": "1310",
    "name": "David"
  },
  {
    "id": "1311",
    "name": "marie"
  },
  {
    "id": "1312",
    "name": "[1-COT] Cyrus [1-COT]"
  },
  {
    "id": "1313",
    "name": "Jim"
  },
  {
    "id": "1314",
    "name": "Ameer Hussain"
  },
  {
    "id": "1315",
    "name": "GEO"
  },
  {
    "id": "1316",
    "name": "Ntinos"
  },
  {
    "id": "1317",
    "name": "Corey_"
  },
  {
    "id": "1318",
    "name": "Elas"
  },
  {
    "id": "1319",
    "name": "[C.S.E.C] QiN3TiX"
  },
  {
    "id": "1320",
    "name": "Prof.Helmut"
  },
  {
    "id": "1321",
    "name": "Pedersen"
  },
  {
    "id": "1322",
    "name": "ArmouredSP"
  },
  {
    "id": "1323",
    "name": "MajorCon"
  },
  {
    "id": "1324",
    "name": "CSF_Skull"
  },
  {
    "id": "1325",
    "name": "CSF_Kanfa"
  },
  {
    "id": "1326",
    "name": "CSF_Flip"
  },
  {
    "id": "1327",
    "name": "CSF_Falc"
  },
  {
    "id": "1328",
    "name": "BLACKJACK69"
  },
  {
    "id": "1329",
    "name": "Dready"
  },
  {
    "id": "1330",
    "name": "CSF_L0rd"
  },
  {
    "id": "1331",
    "name": "CSF_It's Coming Rome"
  },
  {
    "id": "1332",
    "name": "Kaczuska223"
  },
  {
    "id": "1333",
    "name": "[TRD]Serge-UNR"
  },
  {
    "id": "1334",
    "name": "Skipu_12"
  },
  {
    "id": "1335",
    "name": "Śledziu"
  },
  {
    "id": "1336",
    "name": "[SIG]R1220"
  },
  {
    "id": "1337",
    "name": "Jonny raven"
  },
  {
    "id": "1339",
    "name": "[6ème BAP] cassie"
  },
  {
    "id": "1340",
    "name": "Miko"
  },
  {
    "id": "1341",
    "name": "Bartisius"
  },
  {
    "id": "1342",
    "name": "Nearch"
  },
  {
    "id": "1343",
    "name": "[TRD]SKIF"
  },
  {
    "id": "1344",
    "name": "X42X"
  },
  {
    "id": "1345",
    "name": "[6eme BAP] Axel"
  },
  {
    "id": "1346",
    "name": "Green"
  },
  {
    "id": "1347",
    "name": "Pvt. Z. Shiftbolt"
  },
  {
    "id": "1348",
    "name": "[33eSS] L. De Brabant"
  },
  {
    "id": "1349",
    "name": "[33eSS] P. d'Artenois"
  },
  {
    "id": "1350",
    "name": "[33eSS] F de Rive"
  },
  {
    "id": "1351",
    "name": "[33eSS] L. Merckel"
  },
  {
    "id": "1352",
    "name": "[33eSS]S.l'Agneau"
  },
  {
    "id": "1353",
    "name": "[33eSS] Ernst Frühmman"
  },
  {
    "id": "1354",
    "name": "[ML]VSGT  Paladin"
  },
  {
    "id": "1355",
    "name": "[ML] Edwin Brotch"
  },
  {
    "id": "1356",
    "name": "Hans Gruberr"
  },
  {
    "id": "1357",
    "name": "Pawulec"
  },
  {
    "id": "1358",
    "name": "Sgt. X. Noryt"
  },
  {
    "id": "1359",
    "name": "Cpl.J.Juno"
  },
  {
    "id": "1360",
    "name": "smart"
  },
  {
    "id": "1361",
    "name": "[ДП] Breeze"
  },
  {
    "id": "1362",
    "name": "J.Larry"
  },
  {
    "id": "1363",
    "name": "Pzgren.Réz.23PzD"
  },
  {
    "id": "1364",
    "name": "P. Jonathan"
  },
  {
    "id": "1365",
    "name": "Szymek"
  },
  {
    "id": "1366",
    "name": "silwerrobot"
  },
  {
    "id": "1367",
    "name": "=S.O.F=Timo"
  },
  {
    "id": "1368",
    "name": "=S.O.F= Inari"
  },
  {
    "id": "1369",
    "name": "J.Eil. Saruks"
  },
  {
    "id": "1370",
    "name": "Depso"
  },
  {
    "id": "1371",
    "name": "CSF_Koch"
  },
  {
    "id": "1372",
    "name": "Anubissis"
  },
  {
    "id": "1373",
    "name": "Tymek"
  },
  {
    "id": "1374",
    "name": "CSF_Max"
  },
  {
    "id": "1375",
    "name": "Kumer"
  },
  {
    "id": "1376",
    "name": "Nicotron"
  },
  {
    "id": "1377",
    "name": "[FAWR] Nanard"
  },
  {
    "id": "1378",
    "name": "Sonkei"
  },
  {
    "id": "1379",
    "name": "[FAWR]Edwards James"
  },
  {
    "id": "1380",
    "name": "Cooper Lastimosa"
  },
  {
    "id": "1381",
    "name": "[FAWR] Zairtyx"
  },
  {
    "id": "1382",
    "name": "[FAWR] Loann"
  },
  {
    "id": "1383",
    "name": "Hans-Golden"
  },
  {
    "id": "1384",
    "name": "[FAWR] Vlad Dourêve"
  },
  {
    "id": "1385",
    "name": "Bangie"
  },
  {
    "id": "1386",
    "name": "|Kable|™"
  },
  {
    "id": "1387",
    "name": "Mike64"
  },
  {
    "id": "1388",
    "name": "Cpl. L.Sledz"
  },
  {
    "id": "1389",
    "name": "B. Short"
  },
  {
    "id": "1390",
    "name": "R. Thompson"
  },
  {
    "id": "1391",
    "name": "J. Martin"
  },
  {
    "id": "1392",
    "name": "Semi"
  },
  {
    "id": "1393",
    "name": "furygamer"
  },
  {
    "id": "1394",
    "name": "Aiden"
  },
  {
    "id": "1395",
    "name": "CobaNeno"
  },
  {
    "id": "1396",
    "name": "szant"
  },
  {
    "id": "1397",
    "name": "Jadziek"
  },
  {
    "id": "1398",
    "name": "Natashan"
  },
  {
    "id": "1399",
    "name": "[LCDR] R.Briggs"
  },
  {
    "id": "1400",
    "name": "Kamień-Biały"
  },
  {
    "id": "1401",
    "name": "[FAWR] Gordei Gontcharov"
  },
  {
    "id": "1402",
    "name": "[FAWR] Baku"
  },
  {
    "id": "1403",
    "name": "[LTN]Bobby.C"
  },
  {
    "id": "1404",
    "name": "lusod"
  },
  {
    "id": "1405",
    "name": "Sgt. Hermann"
  },
  {
    "id": "1406",
    "name": "Connall McCarthy"
  },
  {
    "id": "1407",
    "name": "Mass"
  },
  {
    "id": "1408",
    "name": "M1ke"
  },
  {
    "id": "1409",
    "name": "ryan"
  },
  {
    "id": "1410",
    "name": "LCpl. Pete"
  },
  {
    "id": "1411",
    "name": "Nemesis"
  },
  {
    "id": "1412",
    "name": "Azariah"
  },
  {
    "id": "1413",
    "name": "InfadelC"
  },
  {
    "id": "1414",
    "name": "Ld.Acm M.Liam"
  },
  {
    "id": "1415",
    "name": "1stTpr. F. Survivor"
  },
  {
    "id": "1416",
    "name": "Pte. P. Stephen"
  },
  {
    "id": "1417",
    "name": "P. Rodrig"
  },
  {
    "id": "1419",
    "name": "[PLH] Twigking"
  },
  {
    "id": "1420",
    "name": "[FAWR] Loutre"
  },
  {
    "id": "1421",
    "name": "Gator"
  },
  {
    "id": "1422",
    "name": "[CTU] walgia"
  },
  {
    "id": "1423",
    "name": "Firaxo"
  },
  {
    "id": "1424",
    "name": "Giovanni Costello"
  },
  {
    "id": "1425",
    "name": "1stPte. J. Bishops"
  },
  {
    "id": "1426",
    "name": "Cpt. A. Astra"
  },
  {
    "id": "1427",
    "name": "Johny Depp"
  },
  {
    "id": "1428",
    "name": "rhyswilliams999"
  },
  {
    "id": "1429",
    "name": "[~StB~]PaverLight"
  },
  {
    "id": "1430",
    "name": "ReBeL"
  },
  {
    "id": "1431",
    "name": "[StB]Riedler"
  },
  {
    "id": "1432",
    "name": "[FAWR] Lucien"
  },
  {
    "id": "1433",
    "name": "[FAWR] Hubert Trepel"
  },
  {
    "id": "1434",
    "name": "[FAWR] White"
  },
  {
    "id": "1435",
    "name": "[FAWR] slucky"
  },
  {
    "id": "1436",
    "name": "[FAWR] Vasky"
  },
  {
    "id": "1437",
    "name": "S. Lynx"
  },
  {
    "id": "1438",
    "name": "† Templar_ex_ignis †"
  },
  {
    "id": "1439",
    "name": "Falcon"
  },
  {
    "id": "1440",
    "name": "PVT. E. Varg"
  },
  {
    "id": "1441",
    "name": "I-Iobbi"
  },
  {
    "id": "1442",
    "name": "Solek"
  },
  {
    "id": "1443",
    "name": "Pingus"
  },
  {
    "id": "1444",
    "name": "Alban"
  },
  {
    "id": "1445",
    "name": "Psiaq"
  },
  {
    "id": "1446",
    "name": "MaittiWIN"
  },
  {
    "id": "1447",
    "name": "Icek"
  },
  {
    "id": "1448",
    "name": "Galant"
  },
  {
    "id": "1449",
    "name": "Little Tank"
  },
  {
    "id": "1450",
    "name": "[FAWR] Skibur"
  },
  {
    "id": "1451",
    "name": "[FAWR] Limbo"
  },
  {
    "id": "1452",
    "name": "[FAWR] Alexandre Sauer"
  },
  {
    "id": "1453",
    "name": "[FAWR] Bakka49"
  },
  {
    "id": "1454",
    "name": "Joda_cz"
  },
  {
    "id": "1455",
    "name": "Kez"
  },
  {
    "id": "1456",
    "name": "Kenionatus"
  },
  {
    "id": "1457",
    "name": "FRYZ"
  },
  {
    "id": "1458",
    "name": "Cparty"
  },
  {
    "id": "1459",
    "name": "[FAWR] Ethan Price"
  },
  {
    "id": "1460",
    "name": "[TA] uMOC"
  },
  {
    "id": "1462",
    "name": "PIONEER"
  },
  {
    "id": "1463",
    "name": "[TA] Авангард"
  },
  {
    "id": "1464",
    "name": "[TNA] Zuko"
  },
  {
    "id": "1465",
    "name": "Crys_"
  },
  {
    "id": "1466",
    "name": "Sushi"
  },
  {
    "id": "1467",
    "name": "Dark"
  },
  {
    "id": "1468",
    "name": "lobit"
  },
  {
    "id": "1469",
    "name": "[FAWR]Wanted"
  },
  {
    "id": "1470",
    "name": "[FAWR] Cyrus"
  },
  {
    "id": "1471",
    "name": "Ciastkoo"
  },
  {
    "id": "1472",
    "name": "[FAWR] Mulan Fa"
  },
  {
    "id": "1473",
    "name": "[FAWR]doudzzwood"
  },
  {
    "id": "1474",
    "name": "Uryszato"
  },
  {
    "id": "1475",
    "name": "TheAdaamek"
  },
  {
    "id": "1476",
    "name": "ENEMY"
  },
  {
    "id": "1477",
    "name": "Eagletres4"
  },
  {
    "id": "1478",
    "name": "Seegan"
  },
  {
    "id": "1479",
    "name": "Laev"
  },
  {
    "id": "1480",
    "name": "Mvments"
  },
  {
    "id": "1481",
    "name": "Thétard"
  },
  {
    "id": "1482",
    "name": "Migoyan"
  },
  {
    "id": "1483",
    "name": "Nitro"
  },
  {
    "id": "1485",
    "name": "Rkt.Niemann.23PzD"
  },
  {
    "id": "1486",
    "name": "Hellmann.23PzD"
  },
  {
    "id": "1487",
    "name": "Graf-Maximus [RKKA]"
  },
  {
    "id": "1488",
    "name": "Pzgren.Wilke.23PzD"
  },
  {
    "id": "1489",
    "name": "[FAWR] beckert"
  },
  {
    "id": "1490",
    "name": "B. Smith"
  },
  {
    "id": "1491",
    "name": "Damix"
  },
  {
    "id": "1492",
    "name": "Weiss"
  },
  {
    "id": "1493",
    "name": "Primo"
  },
  {
    "id": "1494",
    "name": "Diablo"
  },
  {
    "id": "1495",
    "name": "Michus"
  },
  {
    "id": "1496",
    "name": "ZeBrA"
  },
  {
    "id": "1497",
    "name": "Kelnar"
  },
  {
    "id": "1498",
    "name": "Ivno"
  },
  {
    "id": "1499",
    "name": "Rixuuu"
  },
  {
    "id": "1500",
    "name": "Iskra-10"
  },
  {
    "id": "1501",
    "name": "Cookie"
  },
  {
    "id": "1502",
    "name": "le'Carrefour"
  },
  {
    "id": "1503",
    "name": "Zimmerman"
  },
  {
    "id": "1504",
    "name": "Dima"
  },
  {
    "id": "1505",
    "name": "Corleone"
  },
  {
    "id": "1506",
    "name": "Hauptmann"
  },
  {
    "id": "1507",
    "name": "Lt J. Bert [1RW]"
  },
  {
    "id": "1508",
    "name": "[FAWR] George Ulvitch"
  },
  {
    "id": "1509",
    "name": ".TRS."
  },
  {
    "id": "1511",
    "name": "Mamy"
  },
  {
    "id": "1512",
    "name": "BenO"
  },
  {
    "id": "1513",
    "name": "[UTG] ACR"
  },
  {
    "id": "1514",
    "name": "Ohayo"
  },
  {
    "id": "1515",
    "name": "BanY"
  },
  {
    "id": "1516",
    "name": "Navy"
  },
  {
    "id": "1517",
    "name": "Acer"
  },
  {
    "id": "1518",
    "name": "Reksio"
  },
  {
    "id": "1519",
    "name": "[FAWR] Wang"
  },
  {
    "id": "1520",
    "name": "Alex"
  },
  {
    "id": "1521",
    "name": "Swolla"
  },
  {
    "id": "1523",
    "name": "Pfc. Z. Nicholson"
  },
  {
    "id": "1524",
    "name": "Nordicprophet"
  },
  {
    "id": "1525",
    "name": "CSF_Wulfrin"
  },
  {
    "id": "1526",
    "name": "andy-"
  },
  {
    "id": "1527",
    "name": "Pietrać-_-"
  },
  {
    "id": "1528",
    "name": "Adriantus"
  },
  {
    "id": "1530",
    "name": "Pavlosky"
  },
  {
    "id": "1531",
    "name": "Auelos"
  },
  {
    "id": "1532",
    "name": "[AA] Shy"
  },
  {
    "id": "1533",
    "name": "Mazz38"
  },
  {
    "id": "1534",
    "name": "Olaf"
  },
  {
    "id": "1535",
    "name": "Tolly"
  },
  {
    "id": "1536",
    "name": "[TAS]Nikso"
  },
  {
    "id": "1537",
    "name": "Greenthumb-"
  },
  {
    "id": "1538",
    "name": "Lea_nyx"
  },
  {
    "id": "1539",
    "name": "G.Legs"
  },
  {
    "id": "1540",
    "name": "Mallen"
  },
  {
    "id": "1541",
    "name": "Janizki_Fin"
  },
  {
    "id": "1542",
    "name": "Naffes"
  },
  {
    "id": "1543",
    "name": "[17thRB]Cpl.Adrian"
  },
  {
    "id": "1544",
    "name": "Ash"
  },
  {
    "id": "1545",
    "name": "Mihai"
  },
  {
    "id": "1546",
    "name": "Korvak"
  },
  {
    "id": "1547",
    "name": "Fred"
  },
  {
    "id": "1548",
    "name": "[4IB] C. Taylor"
  },
  {
    "id": "1549",
    "name": "[4IB] O. Dryden"
  },
  {
    "id": "1550",
    "name": "[4IB] J. Skipper"
  },
  {
    "id": "1551",
    "name": "[4IB] S. Banks"
  },
  {
    "id": "1552",
    "name": "PFC France"
  },
  {
    "id": "1553",
    "name": "PFC Van Wyk"
  },
  {
    "id": "1554",
    "name": "PFC Gates"
  },
  {
    "id": "1555",
    "name": "Pvt. Cliff"
  },
  {
    "id": "1556",
    "name": "T5 Rodd"
  },
  {
    "id": "1557",
    "name": "PFC Dogfor"
  },
  {
    "id": "1558",
    "name": "Sgt. Falenty"
  },
  {
    "id": "1559",
    "name": "Arma Jesus"
  },
  {
    "id": "1560",
    "name": "Guy Fieri"
  },
  {
    "id": "1561",
    "name": "Vince"
  },
  {
    "id": "1562",
    "name": "[FAWR] Antacks"
  },
  {
    "id": "1563",
    "name": "Patriot -"
  },
  {
    "id": "1564",
    "name": "A.Muniz"
  },
  {
    "id": "1565",
    "name": "[FAWR] Arsenik"
  },
  {
    "id": "1566",
    "name": "_ReeMeeK_"
  },
  {
    "id": "1567",
    "name": "Alkochochlik"
  },
  {
    "id": "1568",
    "name": "xSteel"
  },
  {
    "id": "1569",
    "name": "Jasin"
  },
  {
    "id": "1570",
    "name": "CSF_Racex"
  },
  {
    "id": "1571",
    "name": "PVT R. Budrys"
  },
  {
    "id": "1572",
    "name": "CSF_IlReverendo"
  },
  {
    "id": "1573",
    "name": "Dedos"
  },
  {
    "id": "1574",
    "name": "Patrykus"
  },
  {
    "id": "1575",
    "name": "Radek"
  },
  {
    "id": "1577",
    "name": "Azvel"
  },
  {
    "id": "1578",
    "name": "Jera"
  },
  {
    "id": "1579",
    "name": "RedEffect"
  },
  {
    "id": "1580",
    "name": "Xmel"
  },
  {
    "id": "1581",
    "name": "baen't"
  },
  {
    "id": "1582",
    "name": "Linkon"
  },
  {
    "id": "1583",
    "name": "jaszczur353"
  },
  {
    "id": "1584",
    "name": "MerX"
  },
  {
    "id": "1585",
    "name": "XENO"
  },
  {
    "id": "1586",
    "name": "Haweł2711"
  },
  {
    "id": "1587",
    "name": "Punisher"
  },
  {
    "id": "1588",
    "name": "ZxC"
  },
  {
    "id": "1590",
    "name": "Archer"
  },
  {
    "id": "1591",
    "name": "Trojan"
  },
  {
    "id": "1592",
    "name": "Krytack"
  }
]